<fbgame source="Tas Football" version="1.3.4" generated="7/19/2022">
 <venue gameid="20220490" visid="LEG" homeid="BEN" visname="Legio XIII Roma" homename="Bengals Brescia"
      date="6/4/2022" location="Brescia" stadium="Enrico Cico Nova"
      start="21:30" end="24:20" leaguegame="Y" nitegame="Y" postseason="Y"
      duration="02:50" attend="160" temp="28 C" wind="no wind" weather="sunny">
  <officials ref="Maghini A." ump="Buondonno P." line="Maraventano V." lj="Di Santo A." bj="Rettani R." sc="Ascari S."></officials>
  <rules qtrs="4" mins="12" downs="4" yds="10" kospot="35" tbspot="20" patspot="3" safspot="20" td="6" fg="3" pat="1" patx="2" saf="2" defpat="2" rouge="1" field="100" toh="3" sackrush="Y" fgaplay="N" netpunttb="Y"></rules>
 </venue>
 <team vh="V" code="" id="LEG" name="Legio XIII Roma" record="1-4" conf-record="1-3" abb="L">
  <linescore prds="4" line="6,9,6,0" score="21">
   <lineprd prd="1" score="6"></lineprd>
   <lineprd prd="2" score="9"></lineprd>
   <lineprd prd="3" score="6"></lineprd>
   <lineprd prd="4" score="0"></lineprd>
  </linescore>
  <totals totoff_plays="52" totoff_yards="219" totoff_avg="4.2">
   <firstdowns no="12" rush="3" pass="5" penalty="4"></firstdowns>
   <penalties no="3" yds="14"></penalties>
   <conversions thirdconv="3" thirdatt="11" fourthconv="0" fourthatt="1"></conversions>
   <fumbles no="3" lost="2"></fumbles>
   <misc yds="0" top="18:06" ona="0" onm="0"></misc>
   <redzone att="2" scores="2" points="9" tdrush="0" tdpass="1" fgmade="1" endfga="0" enddowns="0" endint="0" endfumb="0" endhalf="0" endgame="0"></redzone>
   <rush att="17" yds="66" gain="100" loss="34" td="1" long="64"></rush>
   <pass comp="10" att="35" int="1" yds="153" td="2" long="66" sacks="1" sackyds="4"></pass>
   <rcv no="10" yds="153" td="2" long="66"></rcv>
   <punt no="4" yds="129" long="42" blkd="0" tb="0" fc="0" plus50="0" inside20="0" avg="32.2"></punt>
   <ko no="5" yds="228" ob="0" tb="0"></ko>
   <fg made="1" att="1" long="32" blkd="0"></fg>
   <pat kickatt="2" kickmade="0" passatt="1" passmade="0"></pat>
   <defense tackua="44" tacka="8" tot_tack="52" tflua="3" tfla="2" tflyds="17" sacks="1" sackyds="9" brup="2" ff="1" fr="1" fryds="0"></defense>
   <kr no="9" yds="132" td="0" long="45"></kr>
   <pr no="1" yds="1" td="0" long="1"></pr>
   <scoring td="3" fg="1"></scoring>
  </totals>
  <player name="Cacciola F." shortname="Cacciola F." checkname="F.,CACCIOLA" uni="2" gp="1" code="2">
   <rush att="1" yds="0" gain="0" loss="0" td="0" long="0"></rush>
   <rcv no="4" yds="99" td="2" long="66"></rcv>
   <kr no="3" yds="81" td="0" long="45"></kr>
   <scoring td="2"></scoring>
  </player>
  <player name="Daliana A." shortname="Daliana A." checkname="A.,DALIANA" uni="82" gp="1" code="82">
   <rcv no="2" yds="24" td="0" long="13"></rcv>
   <kr no="4" yds="37" td="0" long="15"></kr>
   <pr no="1" yds="1" td="0" long="1"></pr>
  </player>
  <player name="Esposito L." shortname="Esposito L." checkname="L.,ESPOSITO" uni="7" gp="1" code="7">
   <rush att="2" yds="64" gain="64" loss="0" td="1" long="64"></rush>
   <rcv no="2" yds="7" td="0" long="7"></rcv>
   <kr no="1" yds="14" td="0" long="14"></kr>
   <scoring td="1"></scoring>
  </player>
  <player name="Marza' A." shortname="Marza' A." checkname="A.,MARZA'" uni="84" gp="1" code="84">
   <rcv no="1" yds="19" td="0" long="19"></rcv>
  </player>
  <player name="Congestr&#236; G." shortname="Congestr&#236; G." checkname="G.,CONGESTR&#236;" uni="81" gp="1" code="81">
   <rush att="1" yds="-8" gain="0" loss="8" td="0" long="0"></rush>
   <rcv no="1" yds="4" td="0" long="4"></rcv>
  </player>
  <player name="Fronda A." shortname="Fronda A." checkname="A.,FRONDA" uni="27" gp="1" code="27">
   <rush att="2" yds="5" gain="5" loss="0" td="0" long="5"></rush>
  </player>
  <player name="Cacciola L." shortname="Cacciola L." checkname="L.,CACCIOLA" uni="22" gp="1" code="22">
   <rush att="1" yds="1" gain="1" loss="0" td="0" long="1"></rush>
   <defense tackua="1" tacka="0" tot_tack="1"></defense>
  </player>
  <player name="TEAM" shortname="TEAM" checkname="TEAM" uni="TM" gp="1" code="198">
   <rush att="1" yds="-9" gain="0" loss="9" td="0" long="0"></rush>
   <defense tackua="4" tacka="0" tot_tack="4" ff="1"></defense>
   <kr no="1" yds="0" td="0" long="0"></kr>
   <fumbles no="1" lost="1"></fumbles>
  </player>
  <player name="Fiorucci A." shortname="Fiorucci A." checkname="A.,FIORUCCI" uni="4" gp="1" code="4">
   <pass comp="1" att="3" int="0" yds="4" td="0" long="4" sacks="0" sackyds="0"></pass>
  </player>
  <player name="Ferrao D." shortname="Ferrao D." checkname="D.,FERRAO" uni="32" gp="1" code="32">
   <defense tackua="1" tacka="0" tot_tack="1"></defense>
  </player>
  <player name="Tiraferri A." shortname="Tiraferri A." checkname="A.,TIRAFERRI" uni="35" gp="1" code="35">
   <defense tackua="3" tacka="1" tot_tack="4" tflua="1" tfla="0" tflyds="9" sackua="1" sacka="0" sackyds="9" brup="1" fr="1" fryds="0"></defense>
  </player>
  <player name="Rocchi M." shortname="Rocchi M." checkname="M.,ROCCHI" uni="57" gp="1" code="57">
   <defense tackua="4" tacka="2" tot_tack="6" tflua="1" tfla="1" tflyds="3"></defense>
  </player>
  <player name="Lattanzio G." shortname="Lattanzio G." checkname="G.,LATTANZIO" uni="60" gp="1" code="60">
   <defense tackua="1" tacka="0" tot_tack="1"></defense>
  </player>
  <player name="Fiorito L." shortname="Fiorito L." checkname="L.,FIORITO" uni="61" gp="1" code="61">
   <defense tackua="2" tacka="0" tot_tack="2"></defense>
  </player>
  <player name="Bellini D." shortname="Bellini D." checkname="D.,BELLINI" uni="73" gp="1" code="73">
   <defense tackua="8" tacka="1" tot_tack="9"></defense>
  </player>
  <player name="Bernardini P." shortname="Bernardini P." checkname="P.,BERNARDINI" uni="74" gp="1" code="74">
   <punt no="4" yds="129" long="42" blkd="0" tb="0" fc="0" plus50="0" inside20="0" avg="32.2"></punt>
   <ko no="5" yds="228" ob="0" tb="0"></ko>
   <fg made="1" att="1" long="32" blkd="0"></fg>
   <pat kickatt="2" kickmade="0"></pat>
   <scoring fg="1"></scoring>
  </player>
  <player name="Brisciani M." shortname="Brisciani M." checkname="M.,BRISCIANI" uni="25" gp="1" code="25">
   <defense tackua="4" tacka="1" tot_tack="5"></defense>
  </player>
  <player name="Giachino E." shortname="Giachino E." checkname="E.,GIACHINO" uni="1" gp="1" code="1">
   <rush att="8" yds="3" gain="20" loss="17" td="0" long="13"></rush>
   <pass comp="9" att="32" int="1" yds="149" td="2" long="66" sacks="1" sackyds="4"></pass>
   <pat passatt="1" passmade="0"></pat>
   <fumbles no="2" lost="1"></fumbles>
  </player>
  <player name="Bedetti A." shortname="Bedetti A." checkname="A.,BEDETTI" uni="20" gp="1" code="20">
   <rush att="1" yds="10" gain="10" loss="0" td="0" long="10"></rush>
  </player>
  <player name="De Dominicis N." shortname="De Dominicis N." checkname="DOMINICIS N.,DE" uni="85" gp="1" code="85">
   <defense tackua="5" tacka="1" tot_tack="6" tflua="1" tfla="1" tflyds="5"></defense>
  </player>
  <player name="Peccia A." shortname="Peccia A." checkname="A.,PECCIA" uni="87" gp="1" code="87">
   <defense tackua="1" tacka="0" tot_tack="1"></defense>
  </player>
  <player name="Zampetti L." shortname="Zampetti L." checkname="L.,ZAMPETTI" uni="90" gp="1" code="90">
   <defense tackua="5" tacka="0" tot_tack="5" brup="1"></defense>
  </player>
  <player name="Turano D." shortname="Turano D." checkname="D.,TURANO" uni="99" gp="1" code="99">
   <defense tackua="5" tacka="2" tot_tack="7"></defense>
  </player>
 </team>
 <team vh="H" code="" id="BEN" name="Bengals Brescia" record="5-0" conf-record="4-0" abb="B">
  <linescore prds="4" line="13,18,14,16" score="61">
   <lineprd prd="1" score="13"></lineprd>
   <lineprd prd="2" score="18"></lineprd>
   <lineprd prd="3" score="14"></lineprd>
   <lineprd prd="4" score="16"></lineprd>
  </linescore>
  <totals totoff_plays="65" totoff_yards="587" totoff_avg="9.0">
   <firstdowns no="26" rush="21" pass="5" penalty="0"></firstdowns>
   <penalties no="6" yds="85"></penalties>
   <conversions thirdconv="4" thirdatt="8" fourthconv="0" fourthatt="0"></conversions>
   <fumbles no="1" lost="1"></fumbles>
   <misc yds="0" top="29:54" ona="1" onm="1"></misc>
   <redzone att="10" scores="10" points="61" tdrush="6" tdpass="2" fgmade="2" endfga="0" enddowns="0" endint="0" endfumb="0" endhalf="0" endgame="0"></redzone>
   <rush att="47" yds="459" gain="476" loss="17" td="6" long="44"></rush>
   <pass comp="8" att="18" int="0" yds="128" td="2" long="30" sacks="1" sackyds="9"></pass>
   <rcv no="8" yds="128" td="2" long="30"></rcv>
   <punt no="1" yds="33" long="33" blkd="0" tb="0" fc="0" plus50="0" inside20="0" avg="33.0"></punt>
   <ko no="10" yds="403" ob="0" tb="0"></ko>
   <fg made="2" att="2" long="34" blkd="0"></fg>
   <pat kickatt="7" kickmade="5" rushatt="1" rushmade="1"></pat>
   <defense tackua="25" tacka="2" tot_tack="27" tflua="4" tfla="0" tflyds="24" sacks="1" sackyds="4" brup="2" ff="1" fr="1" fryds="0" int="1" intyds="0"></defense>
   <kr no="5" yds="123" td="0" long="33"></kr>
   <ir no="1" yds="0" td="0" long="0"></ir>
   <scoring td="8" fg="2" patkick="5" patrush="1"></scoring>
  </totals>
  <player name="Orizio N." shortname="Orizio N." checkname="N.,ORIZIO" uni="26" gp="1" code="26">
   <rcv no="3" yds="73" td="1" long="30"></rcv>
   <defense tackua="1" tacka="0" tot_tack="1"></defense>
   <scoring td="1"></scoring>
  </player>
  <player name="Gaggiotti M." shortname="Gaggiotti M." checkname="M.,GAGGIOTTI" uni="5" gp="1" code="5">
   <rush att="1" yds="6" gain="6" loss="0" td="0" long="6"></rush>
   <rcv no="3" yds="30" td="1" long="18"></rcv>
   <kr no="4" yds="114" td="0" long="33"></kr>
   <scoring td="1"></scoring>
  </player>
  <player name="Grespan R." shortname="Grespan R." checkname="R.,GRESPAN" uni="4" gp="1" code="4">
   <rcv no="2" yds="25" td="0" long="16"></rcv>
  </player>
  <player name="Di Tusa I." shortname="Di Tusa I." checkname="TUSA I.,DI" uni="27" gp="1" code="27">
   <rush att="9" yds="61" gain="63" loss="2" td="2" long="14"></rush>
   <scoring td="2"></scoring>
  </player>
  <player name="Trami N." shortname="Trami N." checkname="N.,TRAMI" uni="90" gp="1" code="90">
   <rush att="3" yds="52" gain="52" loss="0" td="0" long="32"></rush>
  </player>
  <player name="Bertoglio G." shortname="Bertoglio G." checkname="G.,BERTOGLIO" uni="17" gp="1" code="17">
   <rush att="2" yds="21" gain="21" loss="0" td="0" long="11"></rush>
   <punt no="1" yds="33" long="33" blkd="0" tb="0" fc="0" plus50="0" inside20="0" avg="33.0"></punt>
  </player>
  <player name="Sbaraini A." shortname="Sbaraini A." checkname="A.,SBARAINI" uni="7" gp="1" code="7">
   <rush att="4" yds="83" gain="83" loss="0" td="0" long="44"></rush>
   <defense tackua="1" tacka="0" tot_tack="1"></defense>
  </player>
  <player name="Bassani L." shortname="Bassani L." checkname="L.,BASSANI" uni="15" gp="1" code="15">
   <defense tackua="6" tacka="0" tot_tack="6" brup="1"></defense>
  </player>
  <player name="Canetta A." shortname="Canetta A." checkname="A.,CANETTA" uni="23" gp="1" code="23">
   <defense tackua="2" tacka="1" tot_tack="3"></defense>
  </player>
  <player name="Barbolla R." shortname="Barbolla R." checkname="R.,BARBOLLA" uni="49" gp="1" code="49">
   <rush att="13" yds="113" gain="113" loss="0" td="1" long="33"></rush>
   <pat rushatt="1" rushmade="1"></pat>
   <kr no="1" yds="9" td="0" long="9"></kr>
   <fumbles no="1" lost="1"></fumbles>
   <scoring td="1" patrush="1"></scoring>
  </player>
  <player name="Tinti G." shortname="Tinti G." checkname="G.,TINTI" uni="10" gp="1" code="10">
   <rush att="15" yds="123" gain="138" loss="15" td="3" long="35"></rush>
   <pass comp="8" att="18" int="0" yds="128" td="2" long="30" sacks="1" sackyds="9"></pass>
   <scoring td="3"></scoring>
  </player>
  <player name="Bianchini M." shortname="Bianchini M." checkname="M.,BIANCHINI" uni="30" gp="1" code="30">
   <ko no="10" yds="403" ob="0" tb="0"></ko>
   <fg made="2" att="2" long="34" blkd="0"></fg>
   <pat kickatt="7" kickmade="5"></pat>
   <scoring fg="2" patkick="5"></scoring>
  </player>
  <player name="Putelli S." shortname="Putelli S." checkname="S.,PUTELLI" uni="32" gp="1" code="32">
   <defense tackua="1" tacka="0" tot_tack="1"></defense>
  </player>
  <player name="Favero M." shortname="Favero M." checkname="M.,FAVERO" uni="40" gp="1" code="40">
   <defense tackua="1" tacka="0" tot_tack="1"></defense>
  </player>
  <player name="Ferrari G." shortname="Ferrari G." checkname="G.,FERRARI" uni="44" gp="1" code="44">
   <defense tackua="1" tacka="0" tot_tack="1" tflua="1" tfla="0" tflyds="2" fr="1" fryds="0"></defense>
  </player>
  <player name="Dainesi A." shortname="Dainesi A." checkname="A.,DAINESI" uni="8" gp="1" code="8">
   <defense tackua="2" tacka="0" tot_tack="2" tflua="1" tfla="0" tflyds="4" sackua="1" sacka="0" sackyds="4"></defense>
  </player>
  <player name="Rota R." shortname="Rota R." checkname="R.,ROTA" uni="50" gp="1" code="50">
   <defense tackua="4" tacka="0" tot_tack="4" brup="1"></defense>
  </player>
  <player name="Maiolini M." shortname="Maiolini M." checkname="M.,MAIOLINI" uni="59" gp="1" code="59">
   <defense tackua="1" tacka="0" tot_tack="1"></defense>
  </player>
  <player name="Viviani M." shortname="Viviani M." checkname="M.,VIVIANI" uni="88" gp="1" code="88">
   <defense tackua="2" tacka="1" tot_tack="3" int="1" intyds="0"></defense>
   <ir no="1" yds="0" td="0" long="0"></ir>
  </player>
  <player name="TEAM" shortname="TEAM" checkname="TEAM" uni="TM" gp="1" code="198">
   <defense tackua="3" tacka="0" tot_tack="3" tflua="2" tfla="0" tflyds="18" ff="1"></defense>
  </player>
 </team>
 <scores>
  <score vh="V" team="LEG" qtr="1" clock="10:19" type="TD" how="PASS" yds="66" scorer="Cacciola F." passer="Giachino E." patby="Bernardini P." pattype="KICK" patres="FAIL" plays="3" drive="73" top="1:41" vscore="6" hscore="0" driveindex="1"></score>
  <score vh="H" team="BEN" qtr="1" clock="07:09" type="TD" how="RUSH" yds="10" scorer="Tinti G." patby="Bianchini M." pattype="KICK" patres="FAIL" plays="6" drive="52" top="3:04" vscore="6" hscore="6" driveindex="2"></score>
  <score vh="H" team="BEN" qtr="1" clock="00:15" type="TD" how="PASS" yds="18" scorer="Gaggiotti M." passer="Tinti G." patby="Bianchini M." pattype="KICK" patres="GOOD" plays="4" drive="61" top="3:10" vscore="6" hscore="13" driveindex="6"></score>
  <score vh="H" team="BEN" qtr="2" clock="10:28" type="TD" how="RUSH" yds="4" scorer="Tinti G." patby="Bianchini M." pattype="KICK" patres="GOOD" plays="5" drive="51" top="1:47" vscore="6" hscore="20" driveindex="7"></score>
  <score vh="V" team="LEG" qtr="2" clock="08:05" type="FG" yds="32" scorer="Bernardini P." plays="11" drive="50" top="2:23" vscore="9" hscore="20" driveindex="8"></score>
  <score vh="H" team="BEN" qtr="2" clock="05:12" type="FG" yds="27" scorer="Bianchini M." plays="6" drive="50" top="2:45" vscore="9" hscore="23" driveindex="9"></score>
  <score vh="H" team="BEN" qtr="2" clock="03:00" type="TD" how="PASS" yds="30" scorer="Orizio N." passer="Tinti G." patby="Barbolla R." pattype="RUSH" patres="GOOD" plays="5" drive="48" top="1:00" vscore="9" hscore="31" driveindex="11"></score>
  <score vh="V" team="LEG" qtr="2" clock="00:08" type="TD" how="PASS" yds="7" scorer="Cacciola F." passer="Giachino E." patby="Giachino E." pattype="PASS" patres="FAIL" plays="12" drive="60" top="2:29" vscore="15" hscore="31" driveindex="12"></score>
  <score vh="V" team="LEG" qtr="3" clock="09:17" type="TD" how="RUSH" yds="64" scorer="Esposito L." patby="Bernardini P." pattype="KICK" patres="FAIL" plays="1" drive="64" top="0:13" vscore="21" hscore="31" driveindex="15"></score>
  <score vh="H" team="BEN" qtr="3" clock="07:29" type="TD" how="RUSH" yds="4" scorer="Barbolla R." patby="Bianchini M." pattype="KICK" patres="GOOD" plays="4" drive="47" top="1:33" vscore="21" hscore="38" driveindex="16"></score>
  <score vh="H" team="BEN" qtr="3" clock="03:52" type="TD" how="RUSH" yds="14" scorer="Di Tusa I." patby="Bianchini M." pattype="KICK" patres="GOOD" plays="7" drive="80" top="2:48" vscore="21" hscore="45" driveindex="18"></score>
  <score vh="H" team="BEN" qtr="4" clock="10:27" type="FG" yds="34" scorer="Bianchini M." plays="8" drive="42" top="3:41" vscore="21" hscore="48" driveindex="20"></score>
  <score vh="H" team="BEN" qtr="4" clock="07:00" type="TD" how="RUSH" yds="1" scorer="Tinti G." patby="Bianchini M." pattype="KICK" patres="FAIL" plays="4" drive="65" top="2:00" vscore="21" hscore="54" driveindex="22"></score>
  <score vh="H" team="BEN" qtr="4" clock="02:00" type="TD" how="RUSH" yds="13" scorer="Di Tusa I." patby="Bianchini M." pattype="KICK" patres="GOOD" plays="7" drive="46" top="3:00" vscore="21" hscore="61" driveindex="24"></score>
 </scores>
 <fgas>
  <fga vh="V" team="LEG" kicker="Bernardini P." qtr="2" clock="08:05" distance="32" result="good"></fga>
  <fga vh="H" team="BEN" kicker="Bianchini M." qtr="2" clock="05:12" distance="27" result="good"></fga>
  <fga vh="H" team="BEN" kicker="Bianchini M." qtr="4" clock="10:27" distance="34" result="good"></fga>
 </fgas>
 <drives>
  <drive vh="V" team="LEG" start="KO,1,12:00,27" end="TD,1,10:19,100" plays="3" yards="73" top="1:41" start_how="KO" start_qtr="1" start_time="12:00" start_spot="LEG27" end_how="TD" end_qtr="1" end_time="10:19" end_spot="BEN00" driveindex="1"></drive>
  <drive vh="H" team="BEN" start="KO,1,10:13,48" end="TD,1,07:09,100" plays="6" yards="52" top="3:04" start_how="KO" start_qtr="1" start_time="10:13" start_spot="BEN48" end_how="TD" end_qtr="1" end_time="07:09" end_spot="LEG00" rz="1" driveindex="2"></drive>
  <drive vh="V" team="LEG" start="KO,1,07:09,21" end="PUNT,1,05:59,22" plays="3" yards="1" top="1:10" start_how="KO" start_qtr="1" start_time="07:09" start_spot="LEG21" end_how="PUNT" end_qtr="1" end_time="05:59" end_spot="LEG22" driveindex="3"></drive>
  <drive vh="H" team="BEN" start="PUNT,1,05:59,38" end="PUNT,1,04:00,30" plays="3" yards="-8" top="1:59" start_how="PUNT" start_qtr="1" start_time="05:59" start_spot="BEN38" end_how="PUNT" end_qtr="1" end_time="04:00" end_spot="BEN30" driveindex="4"></drive>
  <drive vh="V" team="LEG" start="PUNT,1,04:00,38" end="PUNT,1,03:25,19" plays="3" yards="-19" top="0:35" start_how="PUNT" start_qtr="1" start_time="04:00" start_spot="LEG38" end_how="PUNT" end_qtr="1" end_time="03:25" end_spot="LEG19" driveindex="5"></drive>
  <drive vh="H" team="BEN" start="PUNT,1,03:25,39" end="TD,1,00:15,100" plays="4" yards="61" top="3:10" start_how="PUNT" start_qtr="1" start_time="03:25" start_spot="BEN39" end_how="TD" end_qtr="1" end_time="00:15" end_spot="LEG00" rz="1" driveindex="6"></drive>
  <drive vh="H" team="BEN" start="KO,1,00:15,49" end="TD,2,10:28,100" plays="5" yards="51" top="1:47" start_how="KO" start_qtr="1" start_time="00:15" start_spot="BEN49" end_how="TD" end_qtr="2" end_time="10:28" end_spot="LEG00" rz="1" driveindex="7"></drive>
  <drive vh="V" team="LEG" start="KO,2,10:28,35" end="FG,2,08:05,85" plays="11" yards="50" top="2:23" start_how="KO" start_qtr="2" start_time="10:28" start_spot="LEG35" end_how="FG" end_qtr="2" end_time="08:05" end_spot="BEN15" rz="1" driveindex="8"></drive>
  <drive vh="H" team="BEN" start="KO,2,07:57,40" end="FG,2,05:12,90" plays="6" yards="50" top="2:45" start_how="KO" start_qtr="2" start_time="07:57" start_spot="BEN40" end_how="FG" end_qtr="2" end_time="05:12" end_spot="LEG10" rz="1" driveindex="9"></drive>
  <drive vh="V" team="LEG" start="KO,2,05:00,34" end="FUMB,2,04:00,48" plays="3" yards="14" top="1:00" start_how="KO" start_qtr="2" start_time="05:00" start_spot="LEG34" end_how="FUMB" end_qtr="2" end_time="04:00" end_spot="LEG48" driveindex="10"></drive>
  <drive vh="H" team="BEN" start="FUMB,2,04:00,52" end="TD,2,03:00,100" plays="5" yards="48" top="1:00" start_how="FUMB" start_qtr="2" start_time="04:00" start_spot="LEG48" end_how="TD" end_qtr="2" end_time="03:00" end_spot="LEG00" rz="1" driveindex="11"></drive>
  <drive vh="V" team="LEG" start="KO,2,02:37,40" end="TD,2,00:08,100" plays="12" yards="60" top="2:29" start_how="KO" start_qtr="2" start_time="02:37" start_spot="LEG40" end_how="TD" end_qtr="2" end_time="00:08" end_spot="BEN00" rz="1" driveindex="12"></drive>
  <drive vh="H" team="BEN" start="KO,2,00:00,47" end="KO,3,12:00,47" plays="0" yards="0" top="0:00" start_how="KO" start_qtr="2" start_time="00:00" start_spot="BEN47" end_how="KO" end_qtr="3" end_time="12:00" end_spot="BEN47" driveindex="13"></drive>
  <drive vh="H" team="BEN" start="KO,3,11:54,37" end="FUMB,3,09:30,64" plays="6" yards="27" top="2:24" start_how="KO" start_qtr="3" start_time="11:54" start_spot="BEN37" end_how="FUMB" end_qtr="3" end_time="09:30" end_spot="LEG36" driveindex="14"></drive>
  <drive vh="V" team="LEG" start="FUMB,3,09:30,36" end="TD,3,09:17,100" plays="1" yards="64" top="0:13" start_how="FUMB" start_qtr="3" start_time="09:30" start_spot="LEG36" end_how="TD" end_qtr="3" end_time="09:17" end_spot="BEN00" driveindex="15"></drive>
  <drive vh="H" team="BEN" start="KO,3,09:02,53" end="TD,3,07:29,100" plays="4" yards="47" top="1:33" start_how="KO" start_qtr="3" start_time="09:02" start_spot="LEG47" end_how="TD" end_qtr="3" end_time="07:29" end_spot="LEG00" rz="1" driveindex="16"></drive>
  <drive vh="V" team="LEG" start="KO,3,07:20,59" end="INT,3,06:40,70" plays="3" yards="11" top="0:40" start_how="KO" start_qtr="3" start_time="07:20" start_spot="BEN41" end_how="INT" end_qtr="3" end_time="06:40" end_spot="BEN30" driveindex="17"></drive>
  <drive vh="H" team="BEN" start="INT,3,06:40,20" end="TD,3,03:52,100" plays="7" yards="80" top="2:48" start_how="INT" start_qtr="3" start_time="06:40" start_spot="BEN20" end_how="TD" end_qtr="3" end_time="03:52" end_spot="LEG00" rz="1" driveindex="18"></drive>
  <drive vh="V" team="LEG" start="KO,3,03:52,52" end="DOWNS,3,02:08,59" plays="4" yards="7" top="1:44" start_how="KO" start_qtr="3" start_time="03:52" start_spot="BEN48" end_how="DOWNS" end_qtr="3" end_time="02:08" end_spot="BEN41" driveindex="19"></drive>
  <drive vh="H" team="BEN" start="DOWNS,3,02:08,41" end="FG,4,10:27,83" plays="8" yards="42" top="3:41" start_how="DOWNS" start_qtr="3" start_time="02:08" start_spot="BEN41" end_how="FG" end_qtr="4" end_time="10:27" end_spot="LEG17" rz="1" driveindex="20"></drive>
  <drive vh="V" team="LEG" start="KO,4,10:21,31" end="PUNT,4,09:00,38" plays="3" yards="7" top="1:21" start_how="KO" start_qtr="4" start_time="10:21" start_spot="LEG31" end_how="PUNT" end_qtr="4" end_time="09:00" end_spot="LEG38" driveindex="21"></drive>
  <drive vh="H" team="BEN" start="PUNT,4,09:00,35" end="TD,4,07:00,100" plays="4" yards="65" top="2:00" start_how="PUNT" start_qtr="4" start_time="09:00" start_spot="BEN35" end_how="TD" end_qtr="4" end_time="07:00" end_spot="LEG00" rz="1" driveindex="22"></drive>
  <drive vh="V" team="LEG" start="KO,4,06:53,30" end="PUNT,4,05:00,26" plays="3" yards="-4" top="1:53" start_how="KO" start_qtr="4" start_time="06:53" start_spot="LEG30" end_how="PUNT" end_qtr="4" end_time="05:00" end_spot="LEG26" driveindex="23"></drive>
  <drive vh="H" team="BEN" start="PUNT,4,05:00,54" end="TD,4,02:00,100" plays="7" yards="46" top="3:00" start_how="PUNT" start_qtr="4" start_time="05:00" start_spot="LEG46" end_how="TD" end_qtr="4" end_time="02:00" end_spot="LEG00" rz="1" driveindex="24"></drive>
  <drive vh="V" team="LEG" start="KO,4,01:48,50" end="HALF,4,00:00,55" plays="3" yards="5" top="1:48" start_how="KO" start_qtr="4" start_time="01:48" start_spot="LEG50" end_how="HALF" end_qtr="4" end_time="00:00" end_spot="BEN45" driveindex="25"></drive>
 </drives>
 <plays format="summary">
  <qtr number="1" text="1st">
   <play hasball="LEG" down="1" togo="10" spot="LEG35" context="V,1,10,V35" playid="0,1,0"
      text="Bengals Brescia win the coin toss, elect to kick" newcontext="V,1,10,V35">
   </play>
   <play hasball="LEG" down="1" togo="10" spot="LEG35" context="V,1,10,V35" playid="0,2,1"
      text="BEN ball on BEN35." newcontext="H,1,10,H35">
   </play>
   <play hasball="BEN" down="1" togo="10" spot="BEN35" context="H,1,10,H35" playid="0,3,2" type="K"
      text="Bianchini M. kickoff 45 yards to the LEG20, Daliana A. return 7 yards to the LEG27 (Bassani L.)." newcontext="V,1,10,V27">
    <p_ko vh="H" name="Bianchini M." gain="45"></p_ko>
    <p_kr vh="V" name="Daliana A." gain="7"></p_kr>
    <p_tk vh="H" name="Bassani L."></p_tk>
   </play>
   <drivestart poss="V,V27,12:00" vh="V" spot="V27" clock="12:00" driveindex="1,2"></drivestart>
   <play hasball="LEG" down="1" togo="10" spot="LEG27" context="V,1,10,V27" playid="1,1,3" type="R"
      text="Esposito L. rush for no gain to the LEG27 (Maiolini M.)." newcontext="V,2,10,V27">
    <p_ru vh="V" name="Esposito L." gain="0"></p_ru>
    <p_tk vh="H" name="Maiolini M."></p_tk>
   </play>
   <play hasball="LEG" down="2" togo="10" spot="LEG27" context="V,2,10,V27" playid="1,2,4" type="P"
      text="Giachino E. pass complete to Cacciola F. for 7 yards to the LEG34 (Dainesi A.)." newcontext="V,3,3,V34">
    <p_pa vh="V" qb="Giachino E." result="COMP" rcv="Cacciola F." gain="7"></p_pa>
    <p_tk vh="H" name="Dainesi A."></p_tk>
   </play>
   <play hasball="LEG" down="3" togo="3" spot="LEG34" context="V,3,3,V34" playid="1,3,5" type="P" first="P" score="Y" clock="10:19"
      text="Giachino E. pass complete to Cacciola F. for 66 yards to the BEN0, 1ST DOWN LEG, TOUCHDOWN, clock 10:19." newcontext="V,1,0,H03">
    <p_pa vh="V" qb="Giachino E." result="COMP" rcv="Cacciola F." gain="66"></p_pa>
   </play>
   <play hasball="LEG" down="1" togo="0" spot="BEN03" context="V,1,0,H03" playid="1,4,6" type="X"
      text="Bernardini P. kick attempt failed." newcontext="V,1,0,V35">
    <p_pat vh="V" name="Bernardini P." qb="Bernardini P." type="K" result="MISSED"></p_pat>
   </play>
   <score V="6" H="0"></score>
   <drivesum plays="3" yards="73" top="1:41" driveindex="1" complete="Y"></drivesum>
   <play hasball="LEG" down="1" togo="0" spot="LEG35" context="V,1,0,V35" playid="1,5,7" type="K"
      text="Bernardini P. kickoff 49 yards to the BEN16, Gaggiotti M. return 32 yards to the BEN48, out-of-bounds." ob="Y" newcontext="H,1,10,H48">
    <p_ko vh="V" name="Bernardini P." gain="49"></p_ko>
    <p_kr vh="H" name="Gaggiotti M." gain="32"></p_kr>
   </play>
   <drivestart poss="H,H48,10:19" vh="H" spot="H48" clock="10:19" driveindex="2,7"></drivestart>
   <play hasball="BEN" down="1" togo="10" spot="BEN48" context="H,1,10,H48" playid="2,1,8" clock="10:13"
      text="BENGALS BRESCIA drive start at 10:13." newcontext="H,1,10,H48">
   </play>
   <play hasball="BEN" down="1" togo="10" spot="BEN48" context="H,1,10,H48" playid="2,2,9" type="R"
      text="Tinti G. rush for 8 yards to the LEG44 (Bellini D.)." newcontext="H,2,2,V44">
    <p_ru vh="H" name="Tinti G." gain="8"></p_ru>
    <p_tk vh="V" name="Bellini D."></p_tk>
   </play>
   <play hasball="BEN" down="2" togo="2" spot="LEG44" context="H,2,2,V44" playid="2,3,10" type="R" first="R"
      text="Barbolla R. rush for 10 yards to the LEG34, 1ST DOWN BEN (Brisciani M.)." newcontext="H,1,10,V34">
    <p_ru vh="H" name="Barbolla R." gain="10"></p_ru>
    <p_tk vh="V" name="Brisciani M."></p_tk>
   </play>
   <play hasball="BEN" down="1" togo="10" spot="LEG34" context="H,1,10,V34" playid="2,4,11" type="P"
      text="Tinti G. pass complete to Gaggiotti M. for 8 yards to the LEG26 (Turano D.)." newcontext="H,2,2,V26">
    <p_pa vh="H" qb="Tinti G." result="COMP" rcv="Gaggiotti M." gain="8"></p_pa>
    <p_tk vh="V" name="Turano D."></p_tk>
   </play>
   <play hasball="BEN" down="2" togo="2" spot="LEG26" context="H,2,2,V26" playid="2,5,12" type="R" first="R"
      text="Barbolla R. rush for 7 yards to the LEG19, 1ST DOWN BEN (Bellini D.)." newcontext="H,1,10,V19">
    <p_ru vh="H" name="Barbolla R." gain="7"></p_ru>
    <p_tk vh="V" name="Bellini D."></p_tk>
   </play>
   <play hasball="BEN" down="1" togo="10" spot="LEG19" context="H,1,10,V19" playid="2,6,13" type="P"
      text="Tinti G. pass complete to Grespan R. for 9 yards to the LEG10, out-of-bounds (Turano D.)." ob="Y" newcontext="H,2,1,V10">
    <p_pa vh="H" qb="Tinti G." result="COMP" rcv="Grespan R." gain="9"></p_pa>
    <p_tk vh="V" name="Turano D."></p_tk>
   </play>
   <play hasball="BEN" down="2" togo="1" spot="LEG10" context="H,2,1,V10" playid="2,7,14" type="#" clock="07:16"
      text="Timeout Legio XIII Roma, clock 07:16." newcontext="H,2,1,V10">
    <p_to vh="V" team="Legio XIII Roma"></p_to>
   </play>
   <play hasball="BEN" down="2" togo="1" spot="LEG10" context="H,2,1,V10" playid="2,8,15" type="R" first="R" score="Y" clock="07:09"
      text="Tinti G. rush for 10 yards to the LEG0, 1ST DOWN BEN, TOUCHDOWN, clock 07:09." newcontext="H,1,0,V03">
    <p_ru vh="H" name="Tinti G." gain="10"></p_ru>
   </play>
   <play hasball="BEN" down="1" togo="0" spot="LEG03" context="H,1,0,V03" playid="2,9,16" type="X"
      text="Bianchini M. kick attempt failed." newcontext="H,1,0,H35">
    <p_pat vh="H" name="Bianchini M." qb="Bianchini M." type="K" result="MISSED"></p_pat>
   </play>
   <score V="6" H="6"></score>
   <drivesum plays="6" yards="52" top="3:04" driveindex="2" complete="Y"></drivesum>
   <play hasball="BEN" down="1" togo="0" spot="BEN35" context="H,1,0,H35" playid="2,10,17" type="K"
      text="Bianchini M. kickoff 45 yards to the LEG20, Daliana A. return 1 yards to the LEG21 (Bassani L.)." newcontext="V,1,10,V21">
    <p_ko vh="H" name="Bianchini M." gain="45"></p_ko>
    <p_kr vh="V" name="Daliana A." gain="1"></p_kr>
    <p_tk vh="H" name="Bassani L."></p_tk>
   </play>
   <drivestart poss="V,V21,07:09" vh="V" spot="V21" clock="07:09" driveindex="3,17"></drivestart>
   <play hasball="LEG" down="1" togo="10" spot="LEG21" context="V,1,10,V21" playid="3,1,18" clock="07:09"
      text="LEGIO XIII ROMA drive start at 07:09." newcontext="V,1,10,V21">
   </play>
   <play hasball="LEG" down="1" togo="10" spot="LEG21" context="V,1,10,V21" playid="3,2,19" type="P"
      text="Giachino E. pass incomplete to Daliana A. (Bassani L.)." newcontext="V,2,10,V21">
    <p_pa vh="V" qb="Giachino E." result="BRUP" rcv="Daliana A."></p_pa>
    <p_bu vh="H" name="Bassani L."></p_bu>
   </play>
   <play hasball="LEG" down="2" togo="10" spot="LEG21" context="V,2,10,V21" playid="3,3,20" type="R"
      text="Cacciola L. rush for 1 yard to the LEG22 (Viviani M.)." newcontext="V,3,9,V22">
    <p_ru vh="V" name="Cacciola L." gain="1"></p_ru>
    <p_tk vh="H" name="Viviani M."></p_tk>
   </play>
   <play hasball="LEG" down="3" togo="9" spot="LEG22" context="V,3,9,V22" playid="3,4,21" type="P"
      text="Giachino E. pass incomplete to Bedetti A.." newcontext="V,4,9,V22">
    <p_pa vh="V" qb="Giachino E." result="INC" rcv="Bedetti A."></p_pa>
   </play>
   <play hasball="LEG" down="4" togo="9" spot="LEG22" context="V,4,9,V22" playid="3,5,22" type="U"
      text="Bernardini P. punt 40 yards to the BEN38." newcontext="H,1,10,H38">
    <p_pu vh="V" name="Bernardini P." gain="40"></p_pu>
   </play>
   <drivesum plays="3" yards="1" top="1:10" driveindex="3" complete="Y"></drivesum>
   <drivestart poss="H,H38,07:09" vh="H" spot="H38" clock="07:09" driveindex="4,22"></drivestart>
   <play hasball="BEN" down="1" togo="10" spot="BEN38" context="H,1,10,H38" playid="4,1,23" clock="05:59"
      text="BENGALS BRESCIA drive start at 05:59." newcontext="H,1,10,H38">
   </play>
   <play hasball="BEN" down="1" togo="10" spot="BEN38" context="H,1,10,H38" playid="4,2,24" type="R"
      text="Sbaraini A. rush for 1 yard to the BEN39 (Bellini D.;Rocchi M.)." newcontext="H,2,9,H39">
    <p_ru vh="H" name="Sbaraini A." gain="1"></p_ru>
    <p_tk vh="V" name="Bellini D." assist="Y"></p_tk>
    <p_tk vh="V" name="Rocchi M." assist="Y"></p_tk>
   </play>
   <play hasball="BEN" down="2" togo="9" spot="BEN39" context="H,2,9,H39" playid="4,3,25" type="P"
      text="Tinti G. pass incomplete to Gaggiotti M.." newcontext="H,3,9,H39">
    <p_pa vh="H" qb="Tinti G." result="INC" rcv="Gaggiotti M."></p_pa>
   </play>
   <play hasball="BEN" down="3" togo="9" spot="BEN39" context="H,3,9,H39" playid="4,4,26" type="P"
      text="Tinti G. sacked for loss of 9 yards to the BEN30 (Tiraferri A.)." newcontext="H,4,18,H30">
    <p_pa vh="H" qb="Tinti G." result="SACK" gain="-9"></p_pa>
    <p_tk vh="V" name="Tiraferri A." sack="Y" tfl="Y"></p_tk>
   </play>
   <play hasball="BEN" down="4" togo="18" spot="BEN30" context="H,4,18,H30" playid="4,5,27" type="U"
      text="Bertoglio G. punt 33 yards to the LEG37, Daliana A. return 1 yards to the LEG38 (Orizio N.)." newcontext="V,1,10,V38">
    <p_pu vh="H" name="Bertoglio G." gain="33"></p_pu>
    <p_pr vh="V" name="Daliana A." gain="1"></p_pr>
    <p_tk vh="H" name="Orizio N."></p_tk>
   </play>
   <drivesum plays="3" yards="-8" top="1:59" driveindex="4" complete="Y"></drivesum>
   <drivestart poss="V,V38,05:59" vh="V" spot="V38" clock="05:59" driveindex="5,27"></drivestart>
   <play hasball="LEG" down="1" togo="10" spot="LEG38" context="V,1,10,V38" playid="5,1,28" clock="04:00"
      text="LEGIO XIII ROMA drive start at 04:00." newcontext="V,1,10,V38">
   </play>
   <play hasball="LEG" down="1" togo="10" spot="LEG38" context="V,1,10,V38" playid="5,2,29" type="R"
      text="TEAM rush for loss of 9 yards to the LEG29." newcontext="V,2,19,V29">
    <p_ru vh="V" name="TEAM" gain="-9"></p_ru>
   </play>
   <play hasball="LEG" down="2" togo="19" spot="LEG29" context="V,2,19,V29" playid="5,3,30" type="R"
      text="Giachino E. rush for loss of 10 yards to the LEG19, fumble forced by TEAM, fumble by Giachino E. recovered by LEG Esposito L. at LEG19." newcontext="V,3,29,V19">
    <p_ru vh="V" name="Giachino E." gain="-10"></p_ru>
    <p_fumb vh="V" name="Giachino E." at="V19" frvh="V" frname="Esposito L."></p_fumb>
    <p_tk vh="H" name="TEAM" ff="Y"></p_tk>
   </play>
   <play hasball="LEG" down="3" togo="29" spot="LEG19" context="V,3,29,V19" playid="5,4,31" type="P"
      text="Giachino E. pass incomplete to Esposito L.." newcontext="V,4,29,V19">
    <p_pa vh="V" qb="Giachino E." result="INC" rcv="Esposito L."></p_pa>
   </play>
   <play hasball="LEG" down="4" togo="29" spot="LEG19" context="V,4,29,V19" playid="5,5,32" type="U"
      text="Bernardini P. punt 42 yards to the BEN39." newcontext="H,1,10,H39">
    <p_pu vh="V" name="Bernardini P." gain="42"></p_pu>
   </play>
   <drivesum plays="3" yards="-19" top="0:35" driveindex="5" complete="Y"></drivesum>
   <drivestart poss="H,H39,04:00" vh="H" spot="H39" clock="04:00" driveindex="6,32"></drivestart>
   <play hasball="BEN" down="1" togo="10" spot="BEN39" context="H,1,10,H39" playid="6,1,33" clock="03:25"
      text="BENGALS BRESCIA drive start at 03:25." newcontext="H,1,10,H39">
   </play>
   <play hasball="BEN" down="1" togo="10" spot="BEN39" context="H,1,10,H39" playid="6,2,34" type="R" first="R"
      text="Tinti G. rush for 35 yards to the LEG26, 1ST DOWN BEN (Fiorito L.)." newcontext="H,1,10,V26">
    <p_ru vh="H" name="Tinti G." gain="35"></p_ru>
    <p_tk vh="V" name="Fiorito L."></p_tk>
   </play>
   <play hasball="BEN" down="1" togo="10" spot="LEG26" context="H,1,10,V26" playid="6,3,35" type="R"
      text="Gaggiotti M. rush for 6 yards to the LEG20 (Turano D.;Brisciani M.)." newcontext="H,2,4,V20">
    <p_ru vh="H" name="Gaggiotti M." gain="6"></p_ru>
    <p_tk vh="V" name="Turano D." assist="Y"></p_tk>
    <p_tk vh="V" name="Brisciani M." assist="Y"></p_tk>
   </play>
   <play hasball="BEN" down="2" togo="4" spot="LEG20" context="H,2,4,V20" playid="6,4,36" type="R"
      text="Tinti G. rush for 2 yards to the LEG18 (Tiraferri A.)." newcontext="H,3,2,V18">
    <p_ru vh="H" name="Tinti G." gain="2"></p_ru>
    <p_tk vh="V" name="Tiraferri A."></p_tk>
   </play>
   <play hasball="BEN" down="3" togo="2" spot="LEG18" context="H,3,2,V18" playid="6,5,37" type="P" first="P" score="Y" clock="00:15"
      text="Tinti G. pass complete to Gaggiotti M. for 18 yards to the LEG0, 1ST DOWN BEN, TOUCHDOWN, clock 00:15." newcontext="H,1,0,V03">
    <p_pa vh="H" qb="Tinti G." result="COMP" rcv="Gaggiotti M." gain="18"></p_pa>
   </play>
   <play hasball="BEN" down="1" togo="0" spot="LEG03" context="H,1,0,V03" playid="6,6,38" type="X" score="Y"
      text="Bianchini M. kick attempt good." newcontext="H,1,0,H35">
    <p_pat vh="H" name="Bianchini M." qb="Bianchini M." type="K" result="GOOD" score="Y"></p_pat>
   </play>
   <score V="6" H="13"></score>
   <drivesum plays="4" yards="61" top="3:10" driveindex="6" complete="Y"></drivesum>
   <play hasball="BEN" down="1" togo="0" spot="BEN35" context="H,1,0,H35" playid="6,7,39" type="K"
      text="Bianchini M. kickoff 14 yards to the BEN49, on-side kick (touch by receiving team), recovered by BEN on BEN49." newcontext="H,1,10,H49">
    <p_ko vh="H" name="Bianchini M." gain="14" result="N"></p_ko>
   </play>
   <drivestart poss="H,H49,00:15" vh="H" spot="H49" clock="00:15" driveindex="7,39"></drivestart>
   <play hasball="BEN" down="1" togo="10" spot="BEN49" context="H,1,10,H49" playid="7,1,40" clock="00:15"
      text="BENGALS BRESCIA drive start at 00:15." newcontext="H,1,10,H49">
   </play>
   <play hasball="BEN" down="1" togo="10" spot="BEN49" context="H,1,10,H49" playid="7,2,41" type="R"
      text="Tinti G. rush for loss of 2 yards to the BEN47 (Rocchi M.;De Dominicis N.)." newcontext="H,2,12,H47">
    <p_ru vh="H" name="Tinti G." gain="-2"></p_ru>
    <p_tk vh="V" name="Rocchi M." tfl="Y" assist="Y"></p_tk>
    <p_tk vh="V" name="De Dominicis N." tfl="Y" assist="Y"></p_tk>
   </play>
   <score qtr="1" V="6" H="13"></score>
   <endqtr></endqtr>
   <qtrsummary vh="V" id="LEG">
    <firstdowns no="1" rush="0" pass="1" penalty="0"></firstdowns>
    <penalties no="0" yds="0"></penalties>
    <conversions thirdconv="1" thirdatt="3" fourthconv="0" fourthatt="0"></conversions>
    <fumbles no="2" lost="1"></fumbles>
    <misc yds="0" top="03:26"></misc>
    <rush att="4" yds="-18" gain="1" loss="19" td="0" long="1"></rush>
    <pass comp="2" att="5" int="0" yds="73" td="1" long="66" sacks="0" sackyds="0"></pass>
    <rcv no="2" yds="73" td="1" long="66"></rcv>
    <punt no="2" yds="82" long="42" blkd="0" tb="0" fc="0" plus50="0" inside20="0" avg="41.0"></punt>
    <ko no="1" yds="49" ob="0" tb="0"></ko>
    <pat kickatt="1" kickmade="0"></pat>
    <defense tackua="8" tacka="6" tot_tack="14" tflua="3" tfla="0" tflyds="13" sacks="1" sackyds="9"></defense>
    <kr no="3" yds="8" td="0" long="7"></kr>
    <pr no="1" yds="1" td="0" long="1"></pr>
    <fumbles no="2" lost="1"></fumbles>
    <scoring td="1"></scoring>
   </qtrsummary>
   <qtrsummary vh="H" id="BEN">
    <firstdowns no="5" rush="4" pass="1" penalty="0"></firstdowns>
    <penalties no="0" yds="0"></penalties>
    <conversions thirdconv="1" thirdatt="2" fourthconv="0" fourthatt="0"></conversions>
    <fumbles no="0" lost="0"></fumbles>
    <misc yds="0" top="08:34"></misc>
    <rush att="10" yds="68" gain="79" loss="11" td="1" long="35"></rush>
    <pass comp="3" att="4" int="0" yds="35" td="1" long="18" sacks="1" sackyds="9"></pass>
    <rcv no="3" yds="35" td="1" long="18"></rcv>
    <punt no="1" yds="33" long="33" blkd="0" tb="0" fc="0" plus50="0" inside20="0" avg="33.0"></punt>
    <ko no="2" yds="90" ob="0" tb="0"></ko>
    <pat kickatt="2" kickmade="1"></pat>
    <defense tackua="7" tacka="0" tot_tack="7" tflua="1" tfla="0" tflyds="10" sacks="0" sackyds="0" brup="1" ff="1"></defense>
    <kr no="1" yds="32" td="0" long="32"></kr>
    <scoring td="2" patkick="1"></scoring>
   </qtrsummary>
  </qtr>
  <qtr number="2" text="2nd">
   <play hasball="BEN" down="2" togo="12" spot="BEN47" context="H,2,12,H47" playid="7,3,42" type="#" clock="12:00"
      text="Start of 2nd quarter, clock 12:00." newcontext="H,2,12,H47">
   </play>
   <play hasball="BEN" down="2" togo="12" spot="BEN47" context="H,2,12,H47" playid="7,4,43" type="R" first="R"
      text="Di Tusa I. rush for 14 yards to the LEG39, 1ST DOWN BEN (Brisciani M.)." newcontext="H,1,10,V39">
    <p_ru vh="H" name="Di Tusa I." gain="14"></p_ru>
    <p_tk vh="V" name="Brisciani M."></p_tk>
   </play>
   <play hasball="BEN" down="1" togo="10" spot="LEG39" context="H,1,10,V39" playid="7,5,44" type="#" clock="11:27"
      text="Timeout Bengals Brescia, clock 11:27." newcontext="H,1,10,V39">
    <p_to vh="H" team="Bengals Brescia"></p_to>
   </play>
   <play hasball="BEN" down="1" togo="10" spot="LEG39" context="H,1,10,V39" playid="7,6,45" type="P" first="P"
      text="Tinti G. pass complete to Orizio N. for 30 yards to the LEG9, 1ST DOWN BEN (TEAM)." newcontext="H,1,0,V09">
    <p_pa vh="H" qb="Tinti G." result="COMP" rcv="Orizio N." gain="30"></p_pa>
    <p_tk vh="V" name="TEAM"></p_tk>
   </play>
   <play hasball="BEN" down="1" togo="0" spot="LEG09" context="H,1,0,V09" playid="7,7,46" type="R"
      text="Barbolla R. rush for 1 yard to the LEG8 (Bellini D.), PENALTY LEG face mask (Rocchi M.) 4 yards to the LEG4." newcontext="H,1,0,V04">
    <p_ru vh="H" name="Barbolla R." gain="1"></p_ru>
    <p_tk vh="V" name="Bellini D."></p_tk>
    <p_pn vh="V" code="FM" type="face mask" name="Rocchi M." result="ACCEPT" at="V08" yards="4"></p_pn>
   </play>
   <play hasball="BEN" down="1" togo="0" spot="LEG04" context="H,1,0,V04" playid="7,8,47"
      text="1st and 4." newcontext="H,1,0,V04">
   </play>
   <play hasball="BEN" down="1" togo="0" spot="LEG04" context="H,1,0,V04" playid="7,9,48" type="R" score="Y" clock="10:28"
      text="Tinti G. rush for 4 yards to the LEG0, TOUCHDOWN, clock 10:28." newcontext="H,1,0,V03">
    <p_ru vh="H" name="Tinti G." gain="4"></p_ru>
   </play>
   <play hasball="BEN" down="1" togo="0" spot="LEG03" context="H,1,0,V03" playid="7,10,49" type="X" score="Y"
      text="Bianchini M. kick attempt good." newcontext="H,1,0,H35">
    <p_pat vh="H" name="Bianchini M." qb="Bianchini M." type="K" result="GOOD" score="Y"></p_pat>
   </play>
   <score V="6" H="20"></score>
   <drivesum plays="5" yards="51" top="1:47" driveindex="7" complete="Y"></drivesum>
   <play hasball="BEN" down="1" togo="0" spot="BEN35" context="H,1,0,H35" playid="7,11,50" type="K"
      text="Bianchini M. kickoff 30 yards to the LEG35." newcontext="V,1,10,V35">
    <p_ko vh="H" name="Bianchini M." gain="30"></p_ko>
   </play>
   <drivestart poss="V,V35,10:28" vh="V" spot="V35" clock="10:28" driveindex="8,50"></drivestart>
   <play hasball="LEG" down="1" togo="10" spot="LEG35" context="V,1,10,V35" playid="8,1,51" clock="10:28"
      text="LEGIO XIII ROMA drive start at 10:28." newcontext="V,1,10,V35">
   </play>
   <play hasball="LEG" down="1" togo="10" spot="LEG35" context="V,1,10,V35" playid="8,2,52" type="P"
      text="Giachino E. pass incomplete to Cacciola F.." newcontext="V,2,10,V35">
    <p_pa vh="V" qb="Giachino E." result="INC" rcv="Cacciola F."></p_pa>
   </play>
   <play hasball="LEG" down="2" togo="10" spot="LEG35" context="V,2,10,V35" playid="8,3,53" type="P"
      text="Giachino E. pass incomplete to Esposito L.." newcontext="V,3,10,V35">
    <p_pa vh="V" qb="Giachino E." result="INC" rcv="Esposito L."></p_pa>
   </play>
   <play hasball="LEG" down="3" togo="10" spot="LEG35" context="V,3,10,V35" playid="8,4,54" type="P" first="E"
      text="Giachino E. pass incomplete to Daliana A., PENALTY BEN holding (Rota R.) 10 yards to the LEG45, 1ST DOWN LEG." newcontext="V,1,10,V45">
    <p_pa vh="V" qb="Giachino E." result="INC" rcv="Daliana A."></p_pa>
    <p_pn vh="H" code="HO" type="holding" name="Rota R." result="ACCEPT" at="V35" yards="10"></p_pn>
   </play>
   <play hasball="LEG" down="1" togo="10" spot="LEG45" context="V,1,10,V45" playid="8,5,55"
      text="1st and 10." newcontext="V,1,10,V45">
   </play>
   <play hasball="LEG" down="1" togo="10" spot="LEG45" context="V,1,10,V45" playid="8,6,56" type="P"
      text="Giachino E. pass incomplete to Cacciola F., dropped pass." newcontext="V,2,10,V45">
    <p_pa vh="V" qb="Giachino E." result="DROP" rcv="Cacciola F."></p_pa>
   </play>
   <play hasball="LEG" down="2" togo="10" spot="LEG45" context="V,2,10,V45" playid="8,7,57" type="R" first="E"
      text="Giachino E. rush for no gain to the LEG45, out-of-bounds, PENALTY BEN personal foul (Viviani M.) 15 yards to the BEN40, 1ST DOWN LEG." ob="Y" newcontext="V,1,10,H40">
    <p_ru vh="V" name="Giachino E." gain="0"></p_ru>
    <p_pn vh="H" code="PF" type="personal foul" name="Viviani M." result="ACCEPT" at="V45" yards="15"></p_pn>
   </play>
   <play hasball="LEG" down="1" togo="10" spot="BEN40" context="V,1,10,H40" playid="8,8,58"
      text="1st and 10." newcontext="V,1,10,H40">
   </play>
   <play hasball="LEG" down="1" togo="10" spot="BEN40" context="V,1,10,H40" playid="8,9,59" type="R" first="R"
      text="Bedetti A. rush for 10 yards to the BEN30, 1ST DOWN LEG, out-of-bounds (Bassani L.)." ob="Y" newcontext="V,1,10,H30">
    <p_ru vh="V" name="Bedetti A." gain="10"></p_ru>
    <p_tk vh="H" name="Bassani L."></p_tk>
   </play>
   <play hasball="LEG" down="1" togo="10" spot="BEN30" context="V,1,10,H30" playid="8,10,60" type="P"
      text="Giachino E. pass incomplete to Daliana A.." newcontext="V,2,10,H30">
    <p_pa vh="V" qb="Giachino E." result="INC" rcv="Daliana A."></p_pa>
   </play>
   <play hasball="LEG" down="2" togo="10" spot="BEN30" context="V,2,10,H30" playid="8,11,61" type="P" first="E"
      text="Giachino E. pass incomplete to Daliana A. (Rota R.), PENALTY BEN pass interference (Rota R.) 15 yards to the BEN15, 1ST DOWN LEG." newcontext="V,1,10,H15">
    <p_pa vh="V" qb="Giachino E." result="BRUP" rcv="Daliana A."></p_pa>
    <p_pn vh="H" code="PI" type="pass interference" name="Rota R." result="ACCEPT" at="H30" yards="15"></p_pn>
    <p_bu vh="H" name="Rota R."></p_bu>
   </play>
   <play hasball="LEG" down="1" togo="10" spot="BEN15" context="V,1,10,H15" playid="8,12,62"
      text="1st and 10." newcontext="V,1,10,H15">
   </play>
   <play hasball="LEG" down="1" togo="10" spot="BEN15" context="V,1,10,H15" playid="8,13,63" type="P"
      text="Giachino E. pass incomplete to Bedetti A.." newcontext="V,2,10,H15">
    <p_pa vh="V" qb="Giachino E." result="INC" rcv="Bedetti A."></p_pa>
   </play>
   <play hasball="LEG" down="2" togo="10" spot="BEN15" context="V,2,10,H15" playid="8,14,64" type="#" clock="09:07"
      text="Timeout Bengals Brescia, clock 09:07." newcontext="V,2,10,H15">
    <p_to vh="H" team="Bengals Brescia"></p_to>
   </play>
   <play hasball="LEG" down="2" togo="10" spot="BEN15" context="V,2,10,H15" playid="8,15,65" type="P"
      text="Giachino E. pass incomplete to Esposito L., dropped pass." newcontext="V,3,10,H15">
    <p_pa vh="V" qb="Giachino E." result="DROP" rcv="Esposito L."></p_pa>
   </play>
   <play hasball="LEG" down="3" togo="10" spot="BEN15" context="V,3,10,H15" playid="8,16,66" type="R"
      text="Giachino E. rush for no gain to the BEN15, out-of-bounds." ob="Y" newcontext="V,4,10,H15">
    <p_ru vh="V" name="Giachino E." gain="0"></p_ru>
   </play>
   <play hasball="LEG" down="4" togo="10" spot="BEN15" context="V,4,10,H15" playid="8,17,67" type="F" score="Y" clock="08:05"
      text="Bernardini P. field goal attempt from 32 GOOD, clock 08:05." newcontext="V,1,0,V35">
    <p_fg vh="V" name="Bernardini P." distance="32" result="GOOD" score="Y"></p_fg>
   </play>
   <score V="9" H="20"></score>
   <play hasball="LEG" down="1" togo="0" spot="LEG35" context="V,1,0,V35" playid="8,18,68" type="E"
      text="Bernardini P. kickoff 40 yards to the BEN25, PENALTY LEG illegal procedure (Bernardini P.) 5 yards to the LEG30, NO PLAY." newcontext="V,1,0,V30">
    <p_pn vh="V" code="PR" type="illegal procedure" name="Bernardini P." result="ACCEPT" at="V35" yards="5"></p_pn>
   </play>
   <drivesum plays="11" yards="50" top="2:23" driveindex="8" complete="Y"></drivesum>
   <play hasball="LEG" down="1" togo="0" spot="LEG30" context="V,1,0,V30" playid="8,19,69" type="K"
      text="Bernardini P. kickoff 51 yards to the BEN19, Gaggiotti M. return 21 yards to the BEN40 (Zampetti L.)." newcontext="H,1,10,H40">
    <p_ko vh="V" name="Bernardini P." gain="51"></p_ko>
    <p_kr vh="H" name="Gaggiotti M." gain="21"></p_kr>
    <p_tk vh="V" name="Zampetti L."></p_tk>
   </play>
   <drivestart poss="H,H40,08:05" vh="H" spot="H40" clock="08:05" driveindex="9,69"></drivestart>
   <play hasball="BEN" down="1" togo="10" spot="BEN40" context="H,1,10,H40" playid="9,1,70" clock="07:57"
      text="BENGALS BRESCIA drive start at 07:57." newcontext="H,1,10,H40">
   </play>
   <play hasball="BEN" down="1" togo="10" spot="BEN40" context="H,1,10,H40" playid="9,2,71" type="R" first="R"
      text="Barbolla R. rush for 22 yards to the LEG38, 1ST DOWN BEN (Turano D.;Tiraferri A.)." newcontext="H,1,10,V38">
    <p_ru vh="H" name="Barbolla R." gain="22"></p_ru>
    <p_tk vh="V" name="Turano D." assist="Y"></p_tk>
    <p_tk vh="V" name="Tiraferri A." assist="Y"></p_tk>
   </play>
   <play hasball="BEN" down="1" togo="10" spot="LEG38" context="H,1,10,V38" playid="9,3,72" type="#" clock="07:30"
      text="Timeout Legio XIII Roma, clock 07:30." newcontext="H,1,10,V38">
    <p_to vh="V" team="Legio XIII Roma"></p_to>
   </play>
   <play hasball="BEN" down="1" togo="10" spot="LEG38" context="H,1,10,V38" playid="9,4,73" type="R" first="R"
      text="Tinti G. rush for 22 yards to the LEG16, 1ST DOWN BEN (Zampetti L.)." newcontext="H,1,10,V16">
    <p_ru vh="H" name="Tinti G." gain="22"></p_ru>
    <p_tk vh="V" name="Zampetti L."></p_tk>
   </play>
   <play hasball="BEN" down="1" togo="10" spot="LEG16" context="H,1,10,V16" playid="9,5,74" type="R"
      text="Barbolla R. rush for no gain to the LEG16, PENALTY BEN face mask (Barbolla R.) 15 yards to the LEG31." newcontext="H,1,25,V31">
    <p_ru vh="H" name="Barbolla R." gain="0"></p_ru>
    <p_pn vh="H" code="FM" type="face mask" name="Barbolla R." result="ACCEPT" at="V16" yards="15"></p_pn>
   </play>
   <play hasball="BEN" down="1" togo="25" spot="LEG31" context="H,1,25,V31" playid="9,6,75"
      text="1st and 25." newcontext="H,1,25,V31">
   </play>
   <play hasball="BEN" down="1" togo="25" spot="LEG31" context="H,1,25,V31" playid="9,7,76" type="P"
      text="Tinti G. pass incomplete to Gaggiotti M.." newcontext="H,2,25,V31">
    <p_pa vh="H" qb="Tinti G." result="INC" rcv="Gaggiotti M."></p_pa>
   </play>
   <play hasball="BEN" down="2" togo="25" spot="LEG31" context="H,2,25,V31" playid="9,8,77" type="R"
      text="Barbolla R. rush for 16 yards to the LEG15 (Brisciani M.)." newcontext="H,3,9,V15">
    <p_ru vh="H" name="Barbolla R." gain="16"></p_ru>
    <p_tk vh="V" name="Brisciani M."></p_tk>
   </play>
   <play hasball="BEN" down="3" togo="9" spot="LEG15" context="H,3,9,V15" playid="9,9,78" type="R"
      text="Tinti G. rush for 5 yards to the LEG10 (De Dominicis N.)." newcontext="H,4,4,V10">
    <p_ru vh="H" name="Tinti G." gain="5"></p_ru>
    <p_tk vh="V" name="De Dominicis N."></p_tk>
   </play>
   <play hasball="BEN" down="4" togo="4" spot="LEG10" context="H,4,4,V10" playid="9,10,79" type="F" score="Y" clock="05:12"
      text="Bianchini M. field goal attempt from 27 GOOD, clock 05:12." newcontext="H,1,0,H35">
    <p_fg vh="H" name="Bianchini M." distance="27" result="GOOD" score="Y"></p_fg>
   </play>
   <score V="9" H="23"></score>
   <drivesum plays="6" yards="50" top="2:45" driveindex="9" complete="Y"></drivesum>
   <play hasball="BEN" down="1" togo="0" spot="BEN35" context="H,1,0,H35" playid="9,11,80" type="K"
      text="Bianchini M. kickoff 48 yards to the LEG17, Cacciola F. return 17 yards to the LEG34 (Canetta A.)." newcontext="V,1,10,V34">
    <p_ko vh="H" name="Bianchini M." gain="48"></p_ko>
    <p_kr vh="V" name="Cacciola F." gain="17"></p_kr>
    <p_tk vh="H" name="Canetta A."></p_tk>
   </play>
   <drivestart poss="V,V34,05:12" vh="V" spot="V34" clock="05:12" driveindex="10,80"></drivestart>
   <play hasball="LEG" down="1" togo="10" spot="LEG34" context="V,1,10,V34" playid="10,1,81" clock="05:00"
      text="LEGIO XIII ROMA drive start at 05:00." newcontext="V,1,10,V34">
   </play>
   <play hasball="LEG" down="1" togo="10" spot="LEG34" context="V,1,10,V34" playid="10,2,82" type="P"
      text="Giachino E. pass complete to Esposito L. for no gain to the LEG34 (Rota R.)." newcontext="V,2,10,V34">
    <p_pa vh="V" qb="Giachino E." result="COMP" rcv="Esposito L." gain="0"></p_pa>
    <p_tk vh="H" name="Rota R."></p_tk>
   </play>
   <play hasball="LEG" down="2" togo="10" spot="LEG34" context="V,2,10,V34" playid="10,3,83" type="P" first="E"
      text="Giachino E. pass incomplete to Daliana A., PENALTY BEN pass interference (Viviani M.) 15 yards to the LEG49, 1ST DOWN LEG." newcontext="V,1,10,V49">
    <p_pa vh="V" qb="Giachino E." result="INC" rcv="Daliana A."></p_pa>
    <p_pn vh="H" code="PI" type="pass interference" name="Viviani M." result="ACCEPT" at="V34" yards="15"></p_pn>
   </play>
   <play hasball="LEG" down="1" togo="10" spot="LEG49" context="V,1,10,V49" playid="10,4,84"
      text="1st and 10." newcontext="V,1,10,V49">
   </play>
   <play hasball="LEG" down="1" togo="10" spot="LEG49" context="V,1,10,V49" playid="10,5,85" type="R" turnover="F"
      text="Giachino E. rush for loss of 1 yard to the LEG48, fumble by Giachino E. recovered by BEN Ferrari G. at LEG48." newcontext="H,1,10,V48">
    <p_ru vh="V" name="Giachino E." gain="-1"></p_ru>
    <p_fumb vh="V" name="Giachino E." at="V48" frvh="H" frname="Ferrari G."></p_fumb>
   </play>
   <drivesum plays="3" yards="14" top="1:00" driveindex="10" complete="Y"></drivesum>
   <drivestart poss="H,V48,05:00" vh="H" spot="V48" clock="05:00" driveindex="11,85"></drivestart>
   <play hasball="BEN" down="1" togo="10" spot="LEG48" context="H,1,10,V48" playid="11,1,86" clock="04:00"
      text="BENGALS BRESCIA drive start at 04:00." newcontext="H,1,10,V48">
   </play>
   <play hasball="BEN" down="1" togo="10" spot="LEG48" context="H,1,10,V48" playid="11,2,87" type="R" first="R"
      text="Barbolla R. rush for 33 yards to the LEG15, 1ST DOWN BEN (Turano D.)." newcontext="H,1,10,V15">
    <p_ru vh="H" name="Barbolla R." gain="33"></p_ru>
    <p_tk vh="V" name="Turano D."></p_tk>
   </play>
   <play hasball="BEN" down="1" togo="10" spot="LEG15" context="H,1,10,V15" playid="11,3,88" type="P"
      text="Tinti G. pass incomplete (Tiraferri A.)." newcontext="H,2,10,V15">
    <p_pa vh="H" qb="Tinti G." result="BRUP"></p_pa>
    <p_bu vh="V" name="Tiraferri A."></p_bu>
   </play>
   <play hasball="BEN" down="2" togo="10" spot="LEG15" context="H,2,10,V15" playid="11,4,89" type="R"
      text="Tinti G. rush for no gain to the LEG15, PENALTY BEN illegal block (Merli A.) 15 yards to the LEG30." newcontext="H,2,25,V30">
    <p_ru vh="H" name="Tinti G." gain="0"></p_ru>
    <p_pn vh="H" code="BL" type="illegal block" name="Merli A." result="ACCEPT" at="V15" yards="15"></p_pn>
   </play>
   <play hasball="BEN" down="2" togo="25" spot="LEG30" context="H,2,25,V30" playid="11,5,90"
      text="2nd and 25." newcontext="H,2,25,V30">
   </play>
   <play hasball="BEN" down="2" togo="25" spot="LEG30" context="H,2,25,V30" playid="11,6,91" type="P"
      text="Tinti G. pass incomplete to Grespan R., dropped pass." newcontext="H,3,25,V30">
    <p_pa vh="H" qb="Tinti G." result="DROP" rcv="Grespan R."></p_pa>
   </play>
   <play hasball="BEN" down="3" togo="25" spot="LEG30" context="H,3,25,V30" playid="11,7,92" type="P" first="P" score="Y" clock="03:00"
      text="Tinti G. pass complete to Orizio N. for 30 yards to the LEG0, 1ST DOWN BEN, TOUCHDOWN, clock 03:00." newcontext="H,1,0,V03">
    <p_pa vh="H" qb="Tinti G." result="COMP" rcv="Orizio N." gain="30"></p_pa>
   </play>
   <play hasball="BEN" down="1" togo="0" spot="LEG03" context="H,1,0,V03" playid="11,8,93" type="X" score="Y"
      text="Barbolla R. rush attempt good." newcontext="H,1,0,H35">
    <p_pat vh="H" name="Barbolla R." qb="Barbolla R." type="R" result="GOOD" score="Y"></p_pat>
   </play>
   <score V="9" H="31"></score>
   <drivesum plays="5" yards="48" top="1:00" driveindex="11" complete="Y"></drivesum>
   <play hasball="BEN" down="1" togo="0" spot="BEN35" context="H,1,0,H35" playid="11,9,94" type="K"
      text="Bianchini M. kickoff 44 yards to the LEG21, Cacciola F. return 19 yards to the LEG40 (Sbaraini A.)." newcontext="V,1,10,V40">
    <p_ko vh="H" name="Bianchini M." gain="44"></p_ko>
    <p_kr vh="V" name="Cacciola F." gain="19"></p_kr>
    <p_tk vh="H" name="Sbaraini A."></p_tk>
   </play>
   <drivestart poss="V,V40,03:00" vh="V" spot="V40" clock="03:00" driveindex="12,94"></drivestart>
   <play hasball="LEG" down="1" togo="10" spot="LEG40" context="V,1,10,V40" playid="12,1,95" clock="02:37"
      text="LEGIO XIII ROMA drive start at 02:37." newcontext="V,1,10,V40">
   </play>
   <play hasball="LEG" down="1" togo="10" spot="LEG40" context="V,1,10,V40" playid="12,2,96" type="R"
      text="Giachino E. rush for loss of 2 yards to the LEG38 (Ferrari G.)." newcontext="V,2,12,V38">
    <p_ru vh="V" name="Giachino E." gain="-2"></p_ru>
    <p_tk vh="H" name="Ferrari G." tfl="Y"></p_tk>
   </play>
   <play hasball="LEG" down="2" togo="12" spot="LEG38" context="V,2,12,V38" playid="12,3,97" type="P" first="P"
      text="Giachino E. pass complete to Daliana A. for 13 yards to the BEN49, 1ST DOWN LEG, out-of-bounds (Rota R.)." ob="Y" newcontext="V,1,10,H49">
    <p_pa vh="V" qb="Giachino E." result="COMP" rcv="Daliana A." gain="13"></p_pa>
    <p_tk vh="H" name="Rota R."></p_tk>
   </play>
   <play hasball="LEG" down="1" togo="10" spot="BEN49" context="V,1,10,H49" playid="12,4,98" type="P"
      text="Giachino E. pass incomplete to Marza' A.." newcontext="V,2,10,H49">
    <p_pa vh="V" qb="Giachino E." result="INC" rcv="Marza' A."></p_pa>
   </play>
   <play hasball="LEG" down="2" togo="10" spot="BEN49" context="V,2,10,H49" playid="12,5,99" type="P" first="P"
      text="Giachino E. pass complete to Marza' A. for 19 yards to the BEN30, 1ST DOWN LEG, out-of-bounds." ob="Y" newcontext="V,1,10,H30">
    <p_pa vh="V" qb="Giachino E." result="COMP" rcv="Marza' A." gain="19"></p_pa>
   </play>
   <play hasball="LEG" down="1" togo="10" spot="BEN30" context="V,1,10,H30" playid="12,6,100" type="P"
      text="Giachino E. pass incomplete to Daliana A.." newcontext="V,2,10,H30">
    <p_pa vh="V" qb="Giachino E." result="INC" rcv="Daliana A."></p_pa>
   </play>
   <play hasball="LEG" down="2" togo="10" spot="BEN30" context="V,2,10,H30" playid="12,7,101" type="R" first="R"
      text="Giachino E. rush for 13 yards to the BEN17, 1ST DOWN LEG, out-of-bounds." ob="Y" newcontext="V,1,10,H17">
    <p_ru vh="V" name="Giachino E." gain="13"></p_ru>
   </play>
   <play hasball="LEG" down="1" togo="10" spot="BEN17" context="V,1,10,H17" playid="12,8,102" type="P"
      text="Giachino E. pass incomplete to Esposito L.." newcontext="V,2,10,H17">
    <p_pa vh="V" qb="Giachino E." result="INC" rcv="Esposito L."></p_pa>
   </play>
   <play hasball="LEG" down="2" togo="10" spot="BEN17" context="V,2,10,H17" playid="12,9,103" type="P"
      text="Giachino E. pass incomplete." newcontext="V,3,10,H17">
    <p_pa vh="V" qb="Giachino E." result="INC"></p_pa>
   </play>
   <play hasball="LEG" down="3" togo="10" spot="BEN17" context="V,3,10,H17" playid="12,10,104" type="E"
      text="PENALTY LEG false start 5 yards to the BEN22." newcontext="V,3,15,H22">
    <p_pn vh="V" code="FS" type="false start" result="ACCEPT" at="H17" yards="5"></p_pn>
   </play>
   <play hasball="LEG" down="3" togo="15" spot="BEN22" context="V,3,15,H22" playid="12,11,105" type="P" first="P"
      text="Giachino E. pass complete to Cacciola F. for 19 yards to the BEN3, 1ST DOWN LEG (Canetta A.)." newcontext="V,1,0,H03">
    <p_pa vh="V" qb="Giachino E." result="COMP" rcv="Cacciola F." gain="19"></p_pa>
    <p_tk vh="H" name="Canetta A."></p_tk>
   </play>
   <play hasball="LEG" down="1" togo="0" spot="BEN03" context="V,1,0,H03" playid="12,12,106" type="P"
      text="Giachino E. pass incomplete to Bedetti A.." newcontext="V,2,0,H03">
    <p_pa vh="V" qb="Giachino E." result="INC" rcv="Bedetti A."></p_pa>
   </play>
   <play hasball="LEG" down="2" togo="0" spot="BEN03" context="V,2,0,H03" playid="12,13,107" type="P"
      text="Giachino E. sacked for loss of 4 yards to the BEN7 (Dainesi A.)." newcontext="V,3,0,H07">
    <p_pa vh="V" qb="Giachino E." result="SACK" gain="-4"></p_pa>
    <p_tk vh="H" name="Dainesi A." sack="Y" tfl="Y"></p_tk>
   </play>
   <play hasball="LEG" down="3" togo="0" spot="BEN07" context="V,3,0,H07" playid="12,14,108" type="#" clock="00:13"
      text="Timeout Legio XIII Roma, clock 00:13." newcontext="V,3,0,H07">
    <p_to vh="V" team="Legio XIII Roma"></p_to>
   </play>
   <play hasball="LEG" down="3" togo="0" spot="BEN07" context="V,3,0,H07" playid="12,15,109" type="P" score="Y" clock="00:08"
      text="Giachino E. pass complete to Cacciola F. for 7 yards to the BEN0, TOUCHDOWN, clock 00:08." newcontext="V,1,0,H03">
    <p_pa vh="V" qb="Giachino E." result="COMP" rcv="Cacciola F." gain="7"></p_pa>
   </play>
   <play hasball="LEG" down="1" togo="0" spot="BEN03" context="V,1,0,H03" playid="12,16,110" type="X"
      text="Giachino E. pass attempt failed." newcontext="V,1,0,V35">
    <p_pat vh="V" name="Giachino E." qb="Giachino E." type="P" result="MISSED"></p_pat>
   </play>
   <score V="15" H="31"></score>
   <drivesum plays="12" yards="60" top="2:29" driveindex="12" complete="Y"></drivesum>
   <play hasball="LEG" down="1" togo="0" spot="LEG35" context="V,1,0,V35" playid="12,17,111" type="K"
      text="Bernardini P. kickoff 51 yards to the BEN14, Gaggiotti M. return 33 yards to the BEN47, out-of-bounds (TEAM)." ob="Y" newcontext="H,1,10,H47">
    <p_ko vh="V" name="Bernardini P." gain="51"></p_ko>
    <p_kr vh="H" name="Gaggiotti M." gain="33"></p_kr>
    <p_tk vh="V" name="TEAM"></p_tk>
   </play>
   <drivestart poss="H,H47,00:08" vh="H" spot="H47" clock="00:08" driveindex="13,111"></drivestart>
   <play hasball="BEN" down="1" togo="10" spot="BEN47" context="H,1,10,H47" playid="13,1,112" clock="00:00"
      text="BENGALS BRESCIA drive start at 00:00." newcontext="H,1,10,H47">
   </play>
   <score qtr="2" V="15" H="31"></score>
   <endqtr></endqtr>
   <qtrsummary vh="V" id="LEG">
    <firstdowns no="9" rush="2" pass="3" penalty="4"></firstdowns>
    <penalties no="3" yds="14"></penalties>
    <conversions thirdconv="2" thirdatt="4" fourthconv="0" fourthatt="0"></conversions>
    <fumbles no="1" lost="1"></fumbles>
    <misc yds="0" top="06:27"></misc>
    <rush att="7" yds="16" gain="23" loss="7" td="0" long="12"></rush>
    <pass comp="5" att="19" int="0" yds="58" td="1" long="0" sacks="1" sackyds="4"></pass>
    <rcv no="5" yds="58" td="1" long="0"></rcv>
    <ko no="2" yds="102" ob="0" tb="0"></ko>
    <fg made="1" att="1" long="32" blkd="0"></fg>
    <pat passatt="1" passmade="0"></pat>
    <defense tackua="9" tacka="2" tot_tack="11" sacks="1" sackyds="9" brup="1"></defense>
    <kr no="2" yds="36" td="0" long="12"></kr>
    <fumbles no="1" lost="1"></fumbles>
    <scoring td="1" fg="1"></scoring>
   </qtrsummary>
   <qtrsummary vh="H" id="BEN">
    <firstdowns no="6" rush="4" pass="2" penalty="0"></firstdowns>
    <penalties no="6" yds="85"></penalties>
    <conversions thirdconv="1" thirdatt="2" fourthconv="0" fourthatt="0"></conversions>
    <fumbles no="0" lost="0"></fumbles>
    <misc yds="0" top="05:33"></misc>
    <rush att="10" yds="117" gain="117" loss="0" td="1" long="0"></rush>
    <pass comp="2" att="5" int="0" yds="60" td="1" long="12" sacks="0" sackyds="0"></pass>
    <rcv no="2" yds="60" td="1" long="12"></rcv>
    <ko no="3" yds="122" ob="0" tb="0"></ko>
    <fg made="1" att="1" long="27" blkd="0"></fg>
    <pat kickatt="1" kickmade="1" rushatt="1" rushmade="1"></pat>
    <defense tackua="8" tacka="0" tot_tack="8" tflua="2" tfla="0" tflyds="6" sacks="1" sackyds="4" brup="1" fr="1" fryds="0"></defense>
    <kr no="2" yds="54" td="0" long="1"></kr>
    <scoring td="2" fg="1" patkick="1" patrush="1"></scoring>
   </qtrsummary>
  </qtr>
  <qtr number="3" text="3rd">
   <play hasball="BEN" down="1" togo="10" spot="BEN47" context="H,1,10,H47" playid="13,2,113" type="#" clock="12:00"
      text="Start of 3rd quarter, clock 12:00." newcontext="H,1,10,H47">
   </play>
   <play hasball="BEN" down="1" togo="10" spot="BEN47" context="H,1,10,H47" playid="13,3,114"
      text="LEG ball on LEG35." newcontext="V,1,10,V35">
   </play>
   <drivesum plays="0" yards="0" top="0:00" driveindex="13" complete="Y"></drivesum>
   <play hasball="LEG" down="1" togo="10" spot="LEG35" context="V,1,10,V35" playid="13,4,115" type="K"
      text="Bernardini P. kickoff 37 yards to the BEN28, Barbolla R. return 9 yards to the BEN37 (Cacciola L.)." newcontext="H,1,10,H37">
    <p_ko vh="V" name="Bernardini P." gain="37"></p_ko>
    <p_kr vh="H" name="Barbolla R." gain="9"></p_kr>
    <p_tk vh="V" name="Cacciola L."></p_tk>
   </play>
   <drivestart poss="H,H37,12:00" vh="H" spot="H37" clock="12:00" driveindex="14,115"></drivestart>
   <play hasball="BEN" down="1" togo="10" spot="BEN37" context="H,1,10,H37" playid="14,1,116" clock="11:54"
      text="BENGALS BRESCIA drive start at 11:54." newcontext="H,1,10,H37">
   </play>
   <play hasball="BEN" down="1" togo="10" spot="BEN37" context="H,1,10,H37" playid="14,2,117" type="R"
      text="Di Tusa I. rush for 3 yards to the BEN40 (Bellini D.)." newcontext="H,2,7,H40">
    <p_ru vh="H" name="Di Tusa I." gain="3"></p_ru>
    <p_tk vh="V" name="Bellini D."></p_tk>
   </play>
   <play hasball="BEN" down="2" togo="7" spot="BEN40" context="H,2,7,H40" playid="14,3,118" type="R" first="R"
      text="Di Tusa I. rush for 7 yards to the BEN47, 1ST DOWN BEN (Rocchi M.)." newcontext="H,1,10,H47">
    <p_ru vh="H" name="Di Tusa I." gain="7"></p_ru>
    <p_tk vh="V" name="Rocchi M."></p_tk>
   </play>
   <play hasball="BEN" down="1" togo="10" spot="BEN47" context="H,1,10,H47" playid="14,4,119" type="P" first="P"
      text="Tinti G. pass complete to Grespan R. for 16 yards to the LEG37, 1ST DOWN BEN." newcontext="H,1,10,V37">
    <p_pa vh="H" qb="Tinti G." result="COMP" rcv="Grespan R." gain="16"></p_pa>
   </play>
   <play hasball="BEN" down="1" togo="10" spot="LEG37" context="H,1,10,V37" playid="14,5,120" type="R"
      text="Barbolla R. rush for 1 yard to the LEG36 (TEAM)." newcontext="H,2,9,V36">
    <p_ru vh="H" name="Barbolla R." gain="1"></p_ru>
    <p_tk vh="V" name="TEAM"></p_tk>
   </play>
   <play hasball="BEN" down="2" togo="9" spot="LEG36" context="H,2,9,V36" playid="14,6,121" type="P"
      text="Tinti G. pass incomplete to Grespan R., dropped pass." newcontext="H,3,9,V36">
    <p_pa vh="H" qb="Tinti G." result="DROP" rcv="Grespan R."></p_pa>
   </play>
   <play hasball="BEN" down="3" togo="9" spot="LEG36" context="H,3,9,V36" playid="14,7,122" type="R" turnover="F"
      text="Barbolla R. rush for no gain to the LEG36, fumble forced by TEAM, fumble by Barbolla R. recovered by LEG Tiraferri A. at LEG36." newcontext="V,1,10,V36">
    <p_ru vh="H" name="Barbolla R." gain="0"></p_ru>
    <p_fumb vh="H" name="Barbolla R." at="V36" frvh="V" frname="Tiraferri A."></p_fumb>
    <p_tk vh="V" name="TEAM" ff="Y"></p_tk>
   </play>
   <drivesum plays="6" yards="27" top="2:24" driveindex="14" complete="Y"></drivesum>
   <drivestart poss="V,V36,11:54" vh="V" spot="V36" clock="11:54" driveindex="15,122"></drivestart>
   <play hasball="LEG" down="1" togo="10" spot="LEG36" context="V,1,10,V36" playid="15,1,123" clock="09:30"
      text="LEGIO XIII ROMA drive start at 09:30." newcontext="V,1,10,V36">
   </play>
   <play hasball="LEG" down="1" togo="10" spot="LEG36" context="V,1,10,V36" playid="15,2,124" type="R" first="R" score="Y" clock="09:17"
      text="Esposito L. rush for 64 yards to the BEN0, 1ST DOWN LEG, TOUCHDOWN, clock 09:17." newcontext="V,1,0,H03">
    <p_ru vh="V" name="Esposito L." gain="64"></p_ru>
   </play>
   <play hasball="LEG" down="1" togo="0" spot="BEN03" context="V,1,0,H03" playid="15,3,125" type="X"
      text="Bernardini P. kick attempt failed." newcontext="V,1,0,V35">
    <p_pat vh="V" name="Bernardini P." qb="Bernardini P." type="K" result="MISSED"></p_pat>
   </play>
   <score V="21" H="31"></score>
   <drivesum plays="1" yards="64" top="0:13" driveindex="15" complete="Y"></drivesum>
   <play hasball="LEG" down="1" togo="0" spot="LEG35" context="V,1,0,V35" playid="15,4,126" type="K"
      text="Bernardini P. kickoff 40 yards to the BEN25, Gaggiotti M. return 28 yards to the LEG47 (Turano D.)." newcontext="H,1,10,V47">
    <p_ko vh="V" name="Bernardini P." gain="40"></p_ko>
    <p_kr vh="H" name="Gaggiotti M." gain="28"></p_kr>
    <p_tk vh="V" name="Turano D."></p_tk>
   </play>
   <drivestart poss="H,V47,09:17" vh="H" spot="V47" clock="09:17" driveindex="16,126"></drivestart>
   <play hasball="BEN" down="1" togo="10" spot="LEG47" context="H,1,10,V47" playid="16,1,127" clock="09:02"
      text="BENGALS BRESCIA drive start at 09:02." newcontext="H,1,10,V47">
   </play>
   <play hasball="BEN" down="1" togo="10" spot="LEG47" context="H,1,10,V47" playid="16,2,128" type="R" first="R"
      text="Tinti G. rush for 32 yards to the LEG15, 1ST DOWN BEN (Ferrao D.)." newcontext="H,1,10,V15">
    <p_ru vh="H" name="Tinti G." gain="32"></p_ru>
    <p_tk vh="V" name="Ferrao D."></p_tk>
   </play>
   <play hasball="BEN" down="1" togo="10" spot="LEG15" context="H,1,10,V15" playid="16,3,129" type="R"
      text="Di Tusa I. rush for 4 yards to the LEG11 (Zampetti L.)." newcontext="H,2,6,V11">
    <p_ru vh="H" name="Di Tusa I." gain="4"></p_ru>
    <p_tk vh="V" name="Zampetti L."></p_tk>
   </play>
   <play hasball="BEN" down="2" togo="6" spot="LEG11" context="H,2,6,V11" playid="16,4,130" type="R" first="R"
      text="Tinti G. rush for 7 yards to the LEG4, 1ST DOWN BEN (De Dominicis N.)." newcontext="H,1,0,V04">
    <p_ru vh="H" name="Tinti G." gain="7"></p_ru>
    <p_tk vh="V" name="De Dominicis N."></p_tk>
   </play>
   <play hasball="BEN" down="1" togo="0" spot="LEG04" context="H,1,0,V04" playid="16,5,131" type="R" score="Y" clock="07:29"
      text="Barbolla R. rush for 4 yards to the LEG0, TOUCHDOWN, clock 07:29." newcontext="H,1,0,V03">
    <p_ru vh="H" name="Barbolla R." gain="4"></p_ru>
   </play>
   <play hasball="BEN" down="1" togo="0" spot="LEG03" context="H,1,0,V03" playid="16,6,132" type="X" score="Y"
      text="Bianchini M. kick attempt good." newcontext="H,1,0,H35">
    <p_pat vh="H" name="Bianchini M." qb="Bianchini M." type="K" result="GOOD" score="Y"></p_pat>
   </play>
   <score V="21" H="38"></score>
   <drivesum plays="4" yards="47" top="1:33" driveindex="16" complete="Y"></drivesum>
   <play hasball="BEN" down="1" togo="0" spot="BEN35" context="H,1,0,H35" playid="16,7,133" type="K"
      text="Bianchini M. kickoff 51 yards to the LEG14, Cacciola F. return 45 yards to the BEN41 (Rota R.)." newcontext="V,1,10,H41">
    <p_ko vh="H" name="Bianchini M." gain="51"></p_ko>
    <p_kr vh="V" name="Cacciola F." gain="45"></p_kr>
    <p_tk vh="H" name="Rota R."></p_tk>
   </play>
   <drivestart poss="V,H41,07:29" vh="V" spot="H41" clock="07:29" driveindex="17,133"></drivestart>
   <play hasball="LEG" down="1" togo="10" spot="BEN41" context="V,1,10,H41" playid="17,1,134" clock="07:20"
      text="LEGIO XIII ROMA drive start at 07:20." newcontext="V,1,10,H41">
   </play>
   <play hasball="LEG" down="1" togo="10" spot="BEN41" context="V,1,10,H41" playid="17,2,135" type="P" first="P"
      text="Giachino E. pass complete to Daliana A. for 11 yards to the BEN30, 1ST DOWN LEG (Bassani L.)." newcontext="V,1,10,H30">
    <p_pa vh="V" qb="Giachino E." result="COMP" rcv="Daliana A." gain="11"></p_pa>
    <p_tk vh="H" name="Bassani L."></p_tk>
   </play>
   <play hasball="LEG" down="1" togo="10" spot="BEN30" context="V,1,10,H30" playid="17,3,136" type="P"
      text="Giachino E. pass incomplete to Cacciola F.." newcontext="V,2,10,H30">
    <p_pa vh="V" qb="Giachino E." result="INC" rcv="Cacciola F."></p_pa>
   </play>
   <play hasball="LEG" down="2" togo="10" spot="BEN30" context="V,2,10,H30" playid="17,4,137" type="P" turnover="I"
      text="Giachino E. pass intercepted by Viviani M. at the BEN20, Viviani M. return 0 yards to the BEN20." newcontext="H,1,10,H20">
    <p_pa vh="V" qb="Giachino E." result="INT"></p_pa>
    <p_ir vh="H" name="Viviani M." at="H20" gain="0"></p_ir>
   </play>
   <drivesum plays="3" yards="11" top="0:40" driveindex="17" complete="Y"></drivesum>
   <drivestart poss="H,H20,07:20" vh="H" spot="H20" clock="07:20" driveindex="18,137"></drivestart>
   <play hasball="BEN" down="1" togo="10" spot="BEN20" context="H,1,10,H20" playid="18,1,138" clock="06:40"
      text="BENGALS BRESCIA drive start at 06:40." newcontext="H,1,10,H20">
   </play>
   <play hasball="BEN" down="1" togo="10" spot="BEN20" context="H,1,10,H20" playid="18,2,139" type="R"
      text="Di Tusa I. rush for 5 yards to the BEN25 (Lattanzio G.)." newcontext="H,2,5,H25">
    <p_ru vh="H" name="Di Tusa I." gain="5"></p_ru>
    <p_tk vh="V" name="Lattanzio G."></p_tk>
   </play>
   <play hasball="BEN" down="2" togo="5" spot="BEN25" context="H,2,5,H25" playid="18,3,140" type="R"
      text="Di Tusa I. rush for 3 yards to the BEN28 (Zampetti L.)." newcontext="H,3,2,H28">
    <p_ru vh="H" name="Di Tusa I." gain="3"></p_ru>
    <p_tk vh="V" name="Zampetti L."></p_tk>
   </play>
   <play hasball="BEN" down="3" togo="2" spot="BEN28" context="H,3,2,H28" playid="18,4,141" type="R" first="R"
      text="Barbolla R. rush for 14 yards to the BEN42, 1ST DOWN BEN (Turano D.)." newcontext="H,1,10,H42">
    <p_ru vh="H" name="Barbolla R." gain="14"></p_ru>
    <p_tk vh="V" name="Turano D."></p_tk>
   </play>
   <play hasball="BEN" down="1" togo="10" spot="BEN42" context="H,1,10,H42" playid="18,5,142" type="R" first="R"
      text="Trami N. rush for 32 yards to the LEG26, 1ST DOWN BEN (Bellini D.)." newcontext="H,1,10,V26">
    <p_ru vh="H" name="Trami N." gain="32"></p_ru>
    <p_tk vh="V" name="Bellini D."></p_tk>
   </play>
   <play hasball="BEN" down="1" togo="10" spot="LEG26" context="H,1,10,V26" playid="18,6,143" type="P"
      text="Tinti G. pass incomplete to Grespan R.." newcontext="H,2,10,V26">
    <p_pa vh="H" qb="Tinti G." result="INC" rcv="Grespan R."></p_pa>
   </play>
   <play hasball="BEN" down="2" togo="10" spot="LEG26" context="H,2,10,V26" playid="18,7,144" type="R" first="R"
      text="Tinti G. rush for 12 yards to the LEG14, 1ST DOWN BEN (Bellini D.)." newcontext="H,1,10,V14">
    <p_ru vh="H" name="Tinti G." gain="12"></p_ru>
    <p_tk vh="V" name="Bellini D."></p_tk>
   </play>
   <play hasball="BEN" down="1" togo="10" spot="LEG14" context="H,1,10,V14" playid="18,8,145" type="R" first="R" score="Y" clock="03:52"
      text="Di Tusa I. rush for 14 yards to the LEG0, 1ST DOWN BEN, TOUCHDOWN, clock 03:52." newcontext="H,1,0,V03">
    <p_ru vh="H" name="Di Tusa I." gain="14"></p_ru>
   </play>
   <play hasball="BEN" down="1" togo="0" spot="LEG03" context="H,1,0,V03" playid="18,9,146" type="X" score="Y"
      text="Bianchini M. kick attempt good." newcontext="H,1,0,H35">
    <p_pat vh="H" name="Bianchini M." qb="Bianchini M." type="K" result="GOOD" score="Y"></p_pat>
   </play>
   <score V="21" H="45"></score>
   <drivesum plays="7" yards="80" top="2:48" driveindex="18" complete="Y"></drivesum>
   <play hasball="BEN" down="1" togo="0" spot="BEN35" context="H,1,0,H35" playid="18,10,147" type="K"
      text="Bianchini M. kickoff 13 yards to the BEN48, downed." newcontext="V,1,10,H48">
    <p_ko vh="H" name="Bianchini M." gain="13"></p_ko>
   </play>
   <drivestart poss="V,H48,03:52" vh="V" spot="H48" clock="03:52" driveindex="19,147"></drivestart>
   <play hasball="LEG" down="1" togo="10" spot="BEN48" context="V,1,10,H48" playid="19,1,148" clock="03:52"
      text="LEGIO XIII ROMA drive start at 03:52." newcontext="V,1,10,H48">
   </play>
   <play hasball="LEG" down="1" togo="10" spot="BEN48" context="V,1,10,H48" playid="19,2,149" type="P"
      text="Giachino E. pass incomplete to Cacciola F.." newcontext="V,2,10,H48">
    <p_pa vh="V" qb="Giachino E." result="INC" rcv="Cacciola F."></p_pa>
   </play>
   <play hasball="LEG" down="2" togo="10" spot="BEN48" context="V,2,10,H48" playid="19,3,150" type="R"
      text="Cacciola F. rush for no gain to the BEN48 (Favero M.)." newcontext="V,3,10,H48">
    <p_ru vh="V" name="Cacciola F." gain="0"></p_ru>
    <p_tk vh="H" name="Favero M."></p_tk>
   </play>
   <play hasball="LEG" down="3" togo="10" spot="BEN48" context="V,3,10,H48" playid="19,4,151" type="P"
      text="Giachino E. pass incomplete to Daliana A.." newcontext="V,4,10,H48">
    <p_pa vh="V" qb="Giachino E." result="INC" rcv="Daliana A."></p_pa>
   </play>
   <play hasball="LEG" down="4" togo="10" spot="BEN48" context="V,4,10,H48" playid="19,5,152" type="R"
      text="Giachino E. rush for 7 yards to the BEN41, out-of-bounds." ob="Y" newcontext="H,1,10,H41">
    <p_ru vh="V" name="Giachino E." gain="7"></p_ru>
   </play>
   <drivesum plays="4" yards="7" top="1:44" driveindex="19" complete="Y"></drivesum>
   <drivestart poss="H,H41,03:52" vh="H" spot="H41" clock="03:52" driveindex="20,152"></drivestart>
   <play hasball="BEN" down="1" togo="10" spot="BEN41" context="H,1,10,H41" playid="20,1,153" clock="02:08"
      text="BENGALS BRESCIA drive start at 02:08." newcontext="H,1,10,H41">
   </play>
   <play hasball="BEN" down="1" togo="10" spot="BEN41" context="H,1,10,H41" playid="20,2,154" type="P"
      text="Tinti G. pass complete to Gaggiotti M. for 4 yards to the BEN45 (Fiorito L.)." newcontext="H,2,6,H45">
    <p_pa vh="H" qb="Tinti G." result="COMP" rcv="Gaggiotti M." gain="4"></p_pa>
    <p_tk vh="V" name="Fiorito L."></p_tk>
   </play>
   <play hasball="BEN" down="2" togo="6" spot="BEN45" context="H,2,6,H45" playid="20,3,155" type="R" first="R"
      text="Sbaraini A. rush for 27 yards to the LEG28, 1ST DOWN BEN (Brisciani M.)." newcontext="H,1,10,V28">
    <p_ru vh="H" name="Sbaraini A." gain="27"></p_ru>
    <p_tk vh="V" name="Brisciani M."></p_tk>
   </play>
   <play hasball="BEN" down="1" togo="10" spot="LEG28" context="H,1,10,V28" playid="20,4,156" type="P"
      text="Tinti G. pass incomplete to Leoni S.." newcontext="H,2,10,V28">
    <p_pa vh="H" qb="Tinti G." result="INC" rcv="Leoni S."></p_pa>
   </play>
   <play hasball="BEN" down="2" togo="10" spot="LEG28" context="H,2,10,V28" playid="20,5,157" type="R"
      text="Di Tusa I. rush for loss of 2 yards to the LEG30 (Rocchi M.)." newcontext="H,3,12,V30">
    <p_ru vh="H" name="Di Tusa I." gain="-2"></p_ru>
    <p_tk vh="V" name="Rocchi M." tfl="Y"></p_tk>
   </play>
   <score qtr="3" V="21" H="45"></score>
   <endqtr></endqtr>
   <qtrsummary vh="V" id="LEG">
    <firstdowns no="2" rush="1" pass="1" penalty="0"></firstdowns>
    <penalties no="0" yds="0"></penalties>
    <conversions thirdconv="0" thirdatt="1" fourthconv="0" fourthatt="1"></conversions>
    <fumbles no="0" lost="0"></fumbles>
    <misc yds="0" top="02:46"></misc>
    <rush att="3" yds="71" gain="71" loss="0" td="1" long="51"></rush>
    <pass comp="1" att="5" int="1" yds="11" td="0" long="0" sacks="0" sackyds="0"></pass>
    <rcv no="1" yds="11" td="0" long="0"></rcv>
    <ko no="2" yds="77" ob="0" tb="0"></ko>
    <pat kickatt="1" kickmade="0"></pat>
    <defense tackua="17" tacka="0" tot_tack="17" tflua="1" tfla="0" tflyds="2" sacks="1" sackyds="9" ff="1" fr="1" fryds="0"></defense>
    <kr no="1" yds="45" td="0" long="26"></kr>
    <scoring td="1"></scoring>
   </qtrsummary>
   <qtrsummary vh="H" id="BEN">
    <firstdowns no="9" rush="8" pass="1" penalty="0"></firstdowns>
    <penalties no="0" yds="0"></penalties>
    <conversions thirdconv="1" thirdatt="2" fourthconv="0" fourthatt="0"></conversions>
    <fumbles no="1" lost="1"></fumbles>
    <misc yds="0" top="09:14"></misc>
    <rush att="16" yds="163" gain="165" loss="2" td="2" long="0"></rush>
    <pass comp="2" att="5" int="0" yds="20" td="0" long="0" sacks="0" sackyds="0"></pass>
    <rcv no="2" yds="20" td="0" long="0"></rcv>
    <ko no="2" yds="64" ob="0" tb="0"></ko>
    <pat kickatt="2" kickmade="2"></pat>
    <defense tackua="3" tacka="0" tot_tack="3" sacks="1" sackyds="4" int="1" intyds="0"></defense>
    <kr no="2" yds="37" td="0" long="0"></kr>
    <ir no="1" yds="0" td="0" long="0"></ir>
    <fumbles no="1" lost="1"></fumbles>
    <scoring td="2" patkick="2"></scoring>
   </qtrsummary>
  </qtr>
  <qtr number="4" text="4th">
   <play hasball="BEN" down="3" togo="12" spot="LEG30" context="H,3,12,V30" playid="20,6,158" type="#" clock="12:00"
      text="Start of 4th quarter, clock 12:00." newcontext="H,3,12,V30">
   </play>
   <play hasball="BEN" down="3" togo="12" spot="LEG30" context="H,3,12,V30" playid="20,7,159" type="P" first="P"
      text="Tinti G. pass complete to Orizio N. for 13 yards to the LEG17, 1ST DOWN BEN (Zampetti L.)." newcontext="H,1,10,V17">
    <p_pa vh="H" qb="Tinti G." result="COMP" rcv="Orizio N." gain="13"></p_pa>
    <p_tk vh="V" name="Zampetti L."></p_tk>
   </play>
   <play hasball="BEN" down="1" togo="10" spot="LEG17" context="H,1,10,V17" playid="20,8,160" type="R"
      text="Barbolla R. rush for no gain to the LEG17 (Peccia A.)." newcontext="H,2,10,V17">
    <p_ru vh="H" name="Barbolla R." gain="0"></p_ru>
    <p_tk vh="V" name="Peccia A."></p_tk>
   </play>
   <play hasball="BEN" down="2" togo="10" spot="LEG17" context="H,2,10,V17" playid="20,9,161" type="P"
      text="Tinti G. pass incomplete to Grespan R., dropped pass." newcontext="H,3,10,V17">
    <p_pa vh="H" qb="Tinti G." result="DROP" rcv="Grespan R."></p_pa>
   </play>
   <play hasball="BEN" down="3" togo="10" spot="LEG17" context="H,3,10,V17" playid="20,10,162" type="P"
      text="Tinti G. pass incomplete to Leoni S. (Zampetti L.)." newcontext="H,4,10,V17">
    <p_pa vh="H" qb="Tinti G." result="BRUP" rcv="Leoni S."></p_pa>
    <p_bu vh="V" name="Zampetti L."></p_bu>
   </play>
   <play hasball="BEN" down="4" togo="10" spot="LEG17" context="H,4,10,V17" playid="20,11,163" type="F" score="Y" clock="10:27"
      text="Bianchini M. field goal attempt from 34 GOOD, clock 10:27." newcontext="H,1,0,H35">
    <p_fg vh="H" name="Bianchini M." distance="34" result="GOOD" score="Y"></p_fg>
   </play>
   <score V="21" H="48"></score>
   <drivesum plays="8" yards="42" top="3:41" driveindex="20" complete="Y"></drivesum>
   <play hasball="BEN" down="1" togo="0" spot="BEN35" context="H,1,0,H35" playid="20,12,164" type="K"
      text="Bianchini M. kickoff 48 yards to the LEG17, Daliana A. return 14 yards to the LEG31 (Bassani L.)." newcontext="V,1,10,V31">
    <p_ko vh="H" name="Bianchini M." gain="48"></p_ko>
    <p_kr vh="V" name="Daliana A." gain="14"></p_kr>
    <p_tk vh="H" name="Bassani L."></p_tk>
   </play>
   <drivestart poss="V,V31,10:27" vh="V" spot="V31" clock="10:27" driveindex="21,164"></drivestart>
   <play hasball="LEG" down="1" togo="10" spot="LEG31" context="V,1,10,V31" playid="21,1,165" clock="10:21"
      text="LEGIO XIII ROMA drive start at 10:21." newcontext="V,1,10,V31">
   </play>
   <play hasball="LEG" down="1" togo="10" spot="LEG31" context="V,1,10,V31" playid="21,2,166" type="P"
      text="Giachino E. pass incomplete to Cacciola F.." newcontext="V,2,10,V31">
    <p_pa vh="V" qb="Giachino E." result="INC" rcv="Cacciola F."></p_pa>
   </play>
   <play hasball="LEG" down="2" togo="10" spot="LEG31" context="V,2,10,V31" playid="21,3,167" type="P"
      text="Giachino E. pass complete to Esposito L. for 7 yards to the LEG38 (Canetta A.;Viviani M.)." newcontext="V,3,3,V38">
    <p_pa vh="V" qb="Giachino E." result="COMP" rcv="Esposito L." gain="7"></p_pa>
    <p_tk vh="H" name="Canetta A." assist="Y"></p_tk>
    <p_tk vh="H" name="Viviani M." assist="Y"></p_tk>
   </play>
   <play hasball="LEG" down="3" togo="3" spot="LEG38" context="V,3,3,V38" playid="21,4,168" type="P"
      text="Giachino E. pass incomplete to Cacciola L.." newcontext="V,4,3,V38">
    <p_pa vh="V" qb="Giachino E." result="INC" rcv="Cacciola L."></p_pa>
   </play>
   <play hasball="LEG" down="4" togo="3" spot="LEG38" context="V,4,3,V38" playid="21,5,169" type="U"
      text="Bernardini P. punt 27 yards to the BEN35." newcontext="H,1,10,H35">
    <p_pu vh="V" name="Bernardini P." gain="27"></p_pu>
   </play>
   <drivesum plays="3" yards="7" top="1:21" driveindex="21" complete="Y"></drivesum>
   <drivestart poss="H,H35,10:21" vh="H" spot="H35" clock="10:21" driveindex="22,169"></drivestart>
   <play hasball="BEN" down="1" togo="10" spot="BEN35" context="H,1,10,H35" playid="22,1,170" clock="09:00"
      text="BENGALS BRESCIA drive start at 09:00." newcontext="H,1,10,H35">
   </play>
   <play hasball="BEN" down="1" togo="10" spot="BEN35" context="H,1,10,H35" playid="22,2,171" type="R" first="R"
      text="Sbaraini A. rush for 44 yards to the LEG21, 1ST DOWN BEN, out-of-bounds (De Dominicis N.)." ob="Y" newcontext="H,1,10,V21">
    <p_ru vh="H" name="Sbaraini A." gain="44"></p_ru>
    <p_tk vh="V" name="De Dominicis N."></p_tk>
   </play>
   <play hasball="BEN" down="1" togo="10" spot="LEG21" context="H,1,10,V21" playid="22,3,172" type="R"
      text="Barbolla R. rush for 5 yards to the LEG16 (Rocchi M.)." newcontext="H,2,5,V16">
    <p_ru vh="H" name="Barbolla R." gain="5"></p_ru>
    <p_tk vh="V" name="Rocchi M."></p_tk>
   </play>
   <play hasball="BEN" down="2" togo="5" spot="LEG16" context="H,2,5,V16" playid="22,4,173" type="R" first="R"
      text="Trami N. rush for 15 yards to the LEG1, 1ST DOWN BEN (De Dominicis N.)." newcontext="H,1,0,V01">
    <p_ru vh="H" name="Trami N." gain="15"></p_ru>
    <p_tk vh="V" name="De Dominicis N."></p_tk>
   </play>
   <play hasball="BEN" down="1" togo="0" spot="LEG01" context="H,1,0,V01" playid="22,5,174" type="R" score="Y" clock="07:00"
      text="Tinti G. rush for 1 yard to the LEG0, TOUCHDOWN, clock 07:00." newcontext="H,1,0,V03">
    <p_ru vh="H" name="Tinti G." gain="1"></p_ru>
   </play>
   <play hasball="BEN" down="1" togo="0" spot="LEG03" context="H,1,0,V03" playid="22,6,175" type="X"
      text="Bianchini M. kick attempt failed." newcontext="H,1,0,H35">
    <p_pat vh="H" name="Bianchini M." qb="Bianchini M." type="K" result="MISSED"></p_pat>
   </play>
   <score V="21" H="54"></score>
   <drivesum plays="4" yards="65" top="2:00" driveindex="22" complete="Y"></drivesum>
   <play hasball="BEN" down="1" togo="0" spot="BEN35" context="H,1,0,H35" playid="22,7,176" type="K"
      text="Bianchini M. kickoff 50 yards to the LEG15, Daliana A. return 15 yards to the LEG30 (Bassani L.)." newcontext="V,1,10,V30">
    <p_ko vh="H" name="Bianchini M." gain="50"></p_ko>
    <p_kr vh="V" name="Daliana A." gain="15"></p_kr>
    <p_tk vh="H" name="Bassani L."></p_tk>
   </play>
   <drivestart poss="V,V30,07:00" vh="V" spot="V30" clock="07:00" driveindex="23,176"></drivestart>
   <play hasball="LEG" down="1" togo="10" spot="LEG30" context="V,1,10,V30" playid="23,1,177" clock="06:53"
      text="LEGIO XIII ROMA drive start at 06:53." newcontext="V,1,10,V30">
   </play>
   <play hasball="LEG" down="1" togo="10" spot="LEG30" context="V,1,10,V30" playid="23,2,178" type="P"
      text="Fiorucci A. pass complete to Congestr&#236; G. for 4 yards to the LEG34 (Rota R.)." newcontext="V,2,6,V34">
    <p_pa vh="V" qb="Fiorucci A." result="COMP" rcv="Congestr&#236; G." gain="4"></p_pa>
    <p_tk vh="H" name="Rota R."></p_tk>
   </play>
   <play hasball="LEG" down="2" togo="6" spot="LEG34" context="V,2,6,V34" playid="23,3,179" type="P"
      text="Fiorucci A. pass incomplete to Congestr&#236; G.." newcontext="V,3,6,V34">
    <p_pa vh="V" qb="Fiorucci A." result="INC" rcv="Congestr&#236; G."></p_pa>
   </play>
   <play hasball="LEG" down="3" togo="6" spot="LEG34" context="V,3,6,V34" playid="23,4,180" type="R"
      text="Congestr&#236; G. rush for loss of 8 yards to the LEG26 (TEAM)." newcontext="V,4,14,V26">
    <p_ru vh="V" name="Congestr&#236; G." gain="-8"></p_ru>
    <p_tk vh="H" name="TEAM" tfl="Y"></p_tk>
   </play>
   <play hasball="LEG" down="4" togo="14" spot="LEG26" context="V,4,14,V26" playid="23,5,181" type="U"
      text="Bernardini P. punt 20 yards to the LEG46." newcontext="H,1,10,V46">
    <p_pu vh="V" name="Bernardini P." gain="20"></p_pu>
   </play>
   <drivesum plays="3" yards="-4" top="1:53" driveindex="23" complete="Y"></drivesum>
   <drivestart poss="H,V46,06:53" vh="H" spot="V46" clock="06:53" driveindex="24,181"></drivestart>
   <play hasball="BEN" down="1" togo="10" spot="LEG46" context="H,1,10,V46" playid="24,1,182" clock="05:00"
      text="BENGALS BRESCIA drive start at 05:00." newcontext="H,1,10,V46">
   </play>
   <play hasball="BEN" down="1" togo="10" spot="LEG46" context="H,1,10,V46" playid="24,2,183" type="R" first="R"
      text="Bertoglio G. rush for 11 yards to the LEG35, 1ST DOWN BEN (Bellini D.)." newcontext="H,1,10,V35">
    <p_ru vh="H" name="Bertoglio G." gain="11"></p_ru>
    <p_tk vh="V" name="Bellini D."></p_tk>
   </play>
   <play hasball="BEN" down="1" togo="10" spot="LEG35" context="H,1,10,V35" playid="24,3,184" type="P"
      text="Tinti G. pass incomplete to Magnanini M.." newcontext="H,2,10,V35">
    <p_pa vh="H" qb="Tinti G." result="INC" rcv="Magnanini M."></p_pa>
   </play>
   <play hasball="BEN" down="2" togo="10" spot="LEG35" context="H,2,10,V35" playid="24,4,185" type="R" first="R"
      text="Bertoglio G. rush for 10 yards to the LEG25, 1ST DOWN BEN (Bellini D.)." newcontext="H,1,10,V25">
    <p_ru vh="H" name="Bertoglio G." gain="10"></p_ru>
    <p_tk vh="V" name="Bellini D."></p_tk>
   </play>
   <play hasball="BEN" down="1" togo="10" spot="LEG25" context="H,1,10,V25" playid="24,5,186" type="R"
      text="Trami N. rush for 5 yards to the LEG20 (Tiraferri A.)." newcontext="H,2,5,V20">
    <p_ru vh="H" name="Trami N." gain="5"></p_ru>
    <p_tk vh="V" name="Tiraferri A."></p_tk>
   </play>
   <play hasball="BEN" down="2" togo="5" spot="LEG20" context="H,2,5,V20" playid="24,6,187" type="R" first="R"
      text="Sbaraini A. rush for 11 yards to the LEG9, 1ST DOWN BEN (Rocchi M.)." newcontext="H,1,0,V09">
    <p_ru vh="H" name="Sbaraini A." gain="11"></p_ru>
    <p_tk vh="V" name="Rocchi M."></p_tk>
   </play>
   <play hasball="BEN" down="1" togo="0" spot="LEG09" context="H,1,0,V09" playid="24,7,188" type="R"
      text="Tinti G. rush for loss of 4 yards to the LEG13 (De Dominicis N.)." newcontext="H,2,0,V13">
    <p_ru vh="H" name="Tinti G." gain="-4"></p_ru>
    <p_tk vh="V" name="De Dominicis N." tfl="Y"></p_tk>
   </play>
   <play hasball="BEN" down="2" togo="0" spot="LEG13" context="H,2,0,V13" playid="24,8,189" type="R" score="Y" clock="02:00"
      text="Di Tusa I. rush for 13 yards to the LEG0, TOUCHDOWN, clock 02:00." newcontext="H,1,0,V03">
    <p_ru vh="H" name="Di Tusa I." gain="13"></p_ru>
   </play>
   <play hasball="BEN" down="1" togo="0" spot="LEG03" context="H,1,0,V03" playid="24,9,190" type="X" score="Y"
      text="Bianchini M. kick attempt good." newcontext="H,1,0,H35">
    <p_pat vh="H" name="Bianchini M." qb="Bianchini M." type="K" result="GOOD" score="Y"></p_pat>
   </play>
   <comment text="running clock"></comment>
   <score V="21" H="61"></score>
   <drivesum plays="7" yards="46" top="3:00" driveindex="24" complete="Y"></drivesum>
   <play hasball="BEN" down="1" togo="0" spot="BEN35" context="H,1,0,H35" playid="24,10,192" type="K"
      text="Bianchini M. kickoff 29 yards to the LEG36, Esposito L. return 14 yards to the 50 yardline (TEAM)." newcontext="V,1,10,V50">
    <p_ko vh="H" name="Bianchini M." gain="29"></p_ko>
    <p_kr vh="V" name="Esposito L." gain="14"></p_kr>
    <p_tk vh="H" name="TEAM"></p_tk>
   </play>
   <drivestart poss="V,V50,02:00" vh="V" spot="V50" clock="02:00" driveindex="25,192"></drivestart>
   <play hasball="LEG" down="1" togo="10" spot="LEG50" context="V,1,10,V50" playid="25,1,193" clock="01:48"
      text="LEGIO XIII ROMA drive start at 01:48." newcontext="V,1,10,V50">
   </play>
   <play hasball="LEG" down="1" togo="10" spot="LEG50" context="V,1,10,V50" playid="25,2,194" type="R"
      text="Fronda A. rush for 5 yards to the BEN45 (Putelli S.)." newcontext="V,2,5,H45">
    <p_ru vh="V" name="Fronda A." gain="5"></p_ru>
    <p_tk vh="H" name="Putelli S."></p_tk>
   </play>
   <play hasball="LEG" down="2" togo="5" spot="BEN45" context="V,2,5,H45" playid="25,3,195" type="R"
      text="Fronda A. rush for no gain to the BEN45 (Viviani M.)." newcontext="V,3,5,H45">
    <p_ru vh="V" name="Fronda A." gain="0"></p_ru>
    <p_tk vh="H" name="Viviani M."></p_tk>
   </play>
   <play hasball="LEG" down="3" togo="5" spot="BEN45" context="V,3,5,H45" playid="25,4,196" type="P"
      text="Fiorucci A. pass incomplete to Lapi O.." newcontext="V,4,5,H45">
    <p_pa vh="V" qb="Fiorucci A." result="INC" rcv="Lapi O."></p_pa>
   </play>
   <play hasball="LEG" down="4" togo="5" spot="BEN45" context="V,4,5,H45" playid="25,5,197" type="#" clock="00:00"
      text="End of game, clock 00:00." newcontext="V,4,5,H45">
   </play>
   <drivesum plays="3" yards="5" top="1:48" driveindex="25" complete="Y"></drivesum>
   <score final="Y" V="21" H="61"></score>
   <endqtr></endqtr>
   <qtrsummary vh="V" id="LEG">
    <firstdowns no="0" rush="0" pass="0" penalty="0"></firstdowns>
    <penalties no="0" yds="0"></penalties>
    <conversions thirdconv="0" thirdatt="3" fourthconv="0" fourthatt="0"></conversions>
    <fumbles no="0" lost="0"></fumbles>
    <misc yds="0" top="05:27"></misc>
    <rush att="3" yds="-3" gain="5" loss="8" td="0" long="0"></rush>
    <pass comp="2" att="6" int="0" yds="11" td="0" long="0" sacks="0" sackyds="0"></pass>
    <rcv no="2" yds="11" td="0" long="0"></rcv>
    <punt no="2" yds="47" long="0" blkd="0" tb="0" fc="0" plus50="0" inside20="0" avg="23.5"></punt>
    <defense tackua="10" tacka="0" tot_tack="10" tflua="1" tfla="0" tflyds="4" sacks="1" sackyds="9" brup="1"></defense>
    <kr no="3" yds="43" td="0" long="0"></kr>
   </qtrsummary>
   <qtrsummary vh="H" id="BEN">
    <firstdowns no="6" rush="5" pass="1" penalty="0"></firstdowns>
    <penalties no="0" yds="0"></penalties>
    <conversions thirdconv="1" thirdatt="2" fourthconv="0" fourthatt="0"></conversions>
    <fumbles no="0" lost="0"></fumbles>
    <misc yds="0" top="06:33"></misc>
    <rush att="11" yds="111" gain="115" loss="4" td="2" long="9"></rush>
    <pass comp="1" att="4" int="0" yds="13" td="0" long="0" sacks="0" sackyds="0"></pass>
    <rcv no="1" yds="13" td="0" long="0"></rcv>
    <ko no="3" yds="127" ob="0" tb="0"></ko>
    <fg made="1" att="1" long="7" blkd="0"></fg>
    <pat kickatt="2" kickmade="1"></pat>
    <defense tackua="7" tacka="2" tot_tack="9" tflua="1" tfla="0" tflyds="8" sacks="1" sackyds="4"></defense>
    <scoring td="2" fg="1" patkick="1"></scoring>
   </qtrsummary>
  </qtr>
  <downtogo hasball="V" id="LEG" down="4" togo="5" spot="BEN45" context="V,4,5,H45" qtr="4" clock="00:00" vtoh="0" htoh="0"
       lastplay="End of game, clock 00:00."></downtogo>
 </plays>
 <message text=""></message>
 <dnp vh="V" id="LEG">
  <player name="Palaia L." checkname="L.,PALAIA" uni="30" gp="0" code="30"></player>
  <player name="Romanini G." checkname="G.,ROMANINI" uni="44" gp="0" code="44"></player>
  <player name="Cavallo F." checkname="F.,CAVALLO" uni="47" gp="0" code="47"></player>
  <player name="Gavioli T." checkname="T.,GAVIOLI" uni="51" gp="0" code="51"></player>
  <player name="Vidali A." checkname="A.,VIDALI" uni="67" gp="0" code="67"></player>
  <player name="Iossa T." checkname="T.,IOSSA" uni="77" gp="0" code="77"></player>
  <player name="Ansalone G." checkname="G.,ANSALONE" uni="78" gp="0" code="78"></player>
  <player name="Lapi O." checkname="O.,LAPI" uni="88" gp="0" code="88"></player>
  <player name="Meduri A." checkname="A.,MEDURI" uni="24" gp="0" code="24"></player>
  <player name="10" checkname="" uni="10" gp="0" code="10"></player>
 </dnp>
 <dnp vh="H" id="BEN">
  <player name="Tessadrelli P." checkname="P.,TESSADRELLI" uni="13" gp="0" code="13"></player>
  <player name="Marini G." checkname="G.,MARINI" uni="21" gp="0" code="21"></player>
  <player name="Leoni S." checkname="S.,LEONI" uni="37" gp="0" code="37"></player>
  <player name="Longhi L." checkname="L.,LONGHI" uni="41" gp="0" code="41"></player>
  <player name="De Marco F." checkname="MARCO F.,DE" uni="43" gp="0" code="43"></player>
  <player name="Gottardo S." checkname="S.,GOTTARDO" uni="53" gp="0" code="53"></player>
  <player name="Zanotti F." checkname="F.,ZANOTTI" uni="55" gp="0" code="55"></player>
  <player name="Calabrese F." checkname="F.,CALABRESE" uni="65" gp="0" code="65"></player>
  <player name="Merli A." checkname="A.,MERLI" uni="66" gp="0" code="66"></player>
  <player name="Magnanini M." checkname="M.,MAGNANINI" uni="80" gp="0" code="80"></player>
  <player name="Bergomi L." checkname="L.,BERGOMI" uni="86" gp="0" code="86"></player>
  <player name="Ragnoli L." checkname="L.,RAGNOLI" uni="6" gp="0" code="6"></player>
  <player name="Lucchese F." checkname="F.,LUCCHESE" uni="99" gp="0" code="99"></player>
 </dnp>
 <longplays thresh="70">
 </longplays>
</fbgame>
